{
  "generatedAt": 1774723173740,
  "source": "archive.org",
  "totalCandidates": 309,
  "playableUnique": 181,
  "totalTracks": 150,
  "categoryCounts": {
    "lap_trinh_vien": 76,
    "ke_toan": 57,
    "phap_che": 2,
    "kinh_doanh": 0,
    "sang_tao": 15
  },
  "categories": {
    "lap_trinh_vien": {
      "label": "Lap trinh vien - Deep focus",
      "description": "Nen nhe, it vocal, giup tap trung code duong dai",
      "tracks": [
        {
          "id": "jamendo-038129:08-268189-Zen Nihilistisch-Spuren.mp3",
          "identifier": "jamendo-038129",
          "title": "Zen Nihilistisch - Musik Metall Minimal I",
          "creator": "Zen Nihilistisch",
          "durationSeconds": 700,
          "url": "https://archive.org/download/jamendo-038129/08-268189-Zen%20Nihilistisch-Spuren.mp3",
          "tags": "zen nihilistisch - musik metall minimal i zen nihilistisch",
          "category": "lap_trinh_vien",
          "categoryScore": 6
        },
        {
          "id": "beautiful-chinese-music-guzheng-bamboo-flute-instrumental-zen-for-relax:Beautiful Chinese Music - Guzheng & Bamboo Flute, Instrumental Zen For Relax.mp3",
          "identifier": "beautiful-chinese-music-guzheng-bamboo-flute-instrumental-zen-for-relax",
          "title": "Beautiful Chinese Music Guzheng & Bamboo Flute, Instrumental Zen For Relax",
          "creator": "SOGEH",
          "durationSeconds": 3053,
          "url": "https://archive.org/download/beautiful-chinese-music-guzheng-bamboo-flute-instrumental-zen-for-relax/Beautiful%20Chinese%20Music%20-%20Guzheng%20%26%20Bamboo%20Flute%2C%20Instrumental%20Zen%20For%20Relax.mp3",
          "tags": "beautiful chinese music guzheng & bamboo flute, instrumental zen for relax sogeh",
          "category": "lap_trinh_vien",
          "categoryScore": 4
        },
        {
          "id": "July312016RevPeterVandersteerehszcHartfordStreetZenDharmaTalk:07302016RevMyo.ogg",
          "identifier": "July312016RevPeterVandersteerehszcHartfordStreetZenDharmaTalk",
          "title": "July 31, 2016 Rev Peter VanDerSteere @HSZC, hartford street zen, dharma talk",
          "creator": "HSZC",
          "durationSeconds": 2352,
          "url": "https://archive.org/download/July312016RevPeterVandersteerehszcHartfordStreetZenDharmaTalk/07302016RevMyo.ogg",
          "tags": "july 31, 2016 rev peter vandersteere @hszc, hartford street zen, dharma talk hszc",
          "category": "lap_trinh_vien",
          "categoryScore": 4
        },
        {
          "id": "august-10-2019-rev.-renshin-bunce:August 10, 2019 – Rev. Renshin Bunce.mp3",
          "identifier": "august-10-2019-rev.-renshin-bunce",
          "title": "August 10, 2019,  Rev. Renshin Bunce @HSZC, hartford street zen, Dharma talk, issanji, issan ji, issan-ji",
          "creator": "HSZC",
          "durationSeconds": 2316,
          "url": "https://archive.org/download/august-10-2019-rev.-renshin-bunce/August%2010%2C%202019%20%E2%80%93%20Rev.%20Renshin%20Bunce.mp3",
          "tags": "august 10, 2019,  rev. renshin bunce @hszc, hartford street zen, dharma talk, issanji, issan ji, issan-ji hszc",
          "category": "lap_trinh_vien",
          "categoryScore": 4
        },
        {
          "id": "zen-buddhist-temple-224039:2019-04-30-Ann-Arbor-Temple-Sunday-Dharma-Talk-by-Haju-Sunim-2019-April-7-PodBean-Development-56978199.mp3",
          "identifier": "zen-buddhist-temple-224039",
          "title": "zen-buddhist-temple-224039",
          "creator": "",
          "durationSeconds": 2280,
          "url": "https://archive.org/download/zen-buddhist-temple-224039/2019-04-30-Ann-Arbor-Temple-Sunday-Dharma-Talk-by-Haju-Sunim-2019-April-7-PodBean-Development-56978199.mp3",
          "tags": "zen-buddhist-temple-224039 ",
          "category": "lap_trinh_vien",
          "categoryScore": 4
        },
        {
          "id": "dni.ncaa.ICCR-064-SP:ICCR-064-SP.mp3",
          "identifier": "dni.ncaa.ICCR-064-SP",
          "title": "Hindustani Music - Instrumental : Flute (Vol. I)",
          "creator": "",
          "durationSeconds": 2223,
          "url": "https://archive.org/download/dni.ncaa.ICCR-064-SP/ICCR-064-SP.mp3",
          "tags": "hindustani music - instrumental : flute (vol. i) ",
          "category": "lap_trinh_vien",
          "categoryScore": 4
        },
        {
          "id": "RevMyoDharmaTalk03062010hszcHartfordStreetZenRevMyoLahey:09Pinnedrev.MyoLaheyHszcDhar.ogg",
          "identifier": "RevMyoDharmaTalk03062010hszcHartfordStreetZenRevMyoLahey",
          "title": "Rev Myo Dharma talk 03 06  2010 @HSZC hartford street zen , Rev Myo Lahey",
          "creator": "HSZC",
          "durationSeconds": 2206,
          "url": "https://archive.org/download/RevMyoDharmaTalk03062010hszcHartfordStreetZenRevMyoLahey/09Pinnedrev.MyoLaheyHszcDhar.ogg",
          "tags": "rev myo dharma talk 03 06  2010 @hszc hartford street zen , rev myo lahey hszc",
          "category": "lap_trinh_vien",
          "categoryScore": 4
        },
        {
          "id": "March202010ThePreceptsrev.PeterVanDerSterreHszcDharmaTalk:11ThePreceptsrev.PeterVanDer.ogg",
          "identifier": "March202010ThePreceptsrev.PeterVanDerSterreHszcDharmaTalk",
          "title": "March 20, 2010 The Precepts (Rev. Peter van der Sterre) HSZC Dharma Talk hartford street zen",
          "creator": "HSZC",
          "durationSeconds": 2201,
          "url": "https://archive.org/download/March202010ThePreceptsrev.PeterVanDerSterreHszcDharmaTalk/11ThePreceptsrev.PeterVanDer.ogg",
          "tags": "march 20, 2010 the precepts (rev. peter van der sterre) hszc dharma talk hartford street zen hszc",
          "category": "lap_trinh_vien",
          "categoryScore": 4
        },
        {
          "id": "the-little-engine-that-could-custom-instrumental:the little engine that could  (CUSTOM INSTRUMENTAL).mp3",
          "identifier": "the-little-engine-that-could-custom-instrumental",
          "title": "The Little Engine That Could ( CUSTOM INSTRUMENTAL)",
          "creator": "",
          "durationSeconds": 1648,
          "url": "https://archive.org/download/the-little-engine-that-could-custom-instrumental/the%20little%20engine%20that%20could%20%20%28CUSTOM%20INSTRUMENTAL%29.mp3",
          "tags": "the little engine that could ( custom instrumental) ",
          "category": "lap_trinh_vien",
          "categoryScore": 4
        },
        {
          "id": "performance-live-set.-experimental.-part-2-ambient-garden-construction-vi:Performance Live Set. Experimental. Part2 Ambient garden \"Construction VI\".mp3",
          "identifier": "performance-live-set.-experimental.-part-2-ambient-garden-construction-vi",
          "title": "Performance Live Set. Experimental. Part 2 Ambient Garden \" Construction VI\"",
          "creator": "Vaia",
          "durationSeconds": 1576,
          "url": "https://archive.org/download/performance-live-set.-experimental.-part-2-ambient-garden-construction-vi/Performance%20Live%20Set.%20Experimental.%20Part2%20Ambient%20garden%20%22Construction%20VI%22.mp3",
          "tags": "performance live set. experimental. part 2 ambient garden \" construction vi\" vaia",
          "category": "lap_trinh_vien",
          "categoryScore": 4
        },
        {
          "id": "june-8-2019-rev.-myo-lahey:June 8, 2019 – Rev. Myo Lahey.mp3",
          "identifier": "june-8-2019-rev.-myo-lahey",
          "title": "Rev Myo Dharma talk 06 08 2019@HSZC hartford street zen , Rev Myo Lahey, issanji, issan ji, issan-ji",
          "creator": "HSZC",
          "durationSeconds": 1454,
          "url": "https://archive.org/download/june-8-2019-rev.-myo-lahey/June%208%2C%202019%20%E2%80%93%20Rev.%20Myo%20Lahey.mp3",
          "tags": "rev myo dharma talk 06 08 2019@hszc hartford street zen , rev myo lahey, issanji, issan ji, issan-ji hszc",
          "category": "lap_trinh_vien",
          "categoryScore": 4
        },
        {
          "id": "RevMyoDharmaTalk04102010hszcHartfordStreetZenRevMyoLahey:14UnobstructedBeingrev.MyoLahe.ogg",
          "identifier": "RevMyoDharmaTalk04102010hszcHartfordStreetZenRevMyoLahey",
          "title": "Rev Myo Dharma talk 04 10  2010 @HSZC hartford street zen , Rev Myo Lahey",
          "creator": "HSZC",
          "durationSeconds": 1349,
          "url": "https://archive.org/download/RevMyoDharmaTalk04102010hszcHartfordStreetZenRevMyoLahey/14UnobstructedBeingrev.MyoLahe.ogg",
          "tags": "rev myo dharma talk 04 10  2010 @hszc hartford street zen , rev myo lahey hszc",
          "category": "lap_trinh_vien",
          "categoryScore": 4
        },
        {
          "id": "dni.ncaa.ICCR-065-SP:ICCR-065-SP.mp3",
          "identifier": "dni.ncaa.ICCR-065-SP",
          "title": "Hindustani Music - Instrumental : Flute (Vol. II)",
          "creator": "",
          "durationSeconds": 1294,
          "url": "https://archive.org/download/dni.ncaa.ICCR-065-SP/ICCR-065-SP.mp3",
          "tags": "hindustani music - instrumental : flute (vol. ii) ",
          "category": "lap_trinh_vien",
          "categoryScore": 4
        },
        {
          "id": "gendozencrossing:gendozencrossing.mp3",
          "identifier": "gendozencrossing",
          "title": "Chaplaincy and the Zen Path",
          "creator": "Puget Sound Zen Center",
          "durationSeconds": 921,
          "url": "https://archive.org/download/gendozencrossing/gendozencrossing.mp3",
          "tags": "chaplaincy and the zen path puget sound zen center",
          "category": "lap_trinh_vien",
          "categoryScore": 4
        },
        {
          "id": "RevMyoDharmaTalk01072017hszcIssanjiHartfordStreetZenRevMyo:RevMyo01072017Jukai.ogg",
          "identifier": "RevMyoDharmaTalk01072017hszcIssanjiHartfordStreetZenRevMyo",
          "title": "Rev Myo Dharma talk 01 07 2017 @HSZC, Issanji, hartford street zen , Rev Myo Lahey",
          "creator": "HSZC",
          "durationSeconds": 820,
          "url": "https://archive.org/download/RevMyoDharmaTalk01072017hszcIssanjiHartfordStreetZenRevMyo/RevMyo01072017Jukai.ogg",
          "tags": "rev myo dharma talk 01 07 2017 @hszc, issanji, hartford street zen , rev myo lahey hszc",
          "category": "lap_trinh_vien",
          "categoryScore": 4
        },
        {
          "id": "zen_hi:Zen_hi1.ogg",
          "identifier": "zen_hi",
          "title": "zen_hi",
          "creator": "",
          "durationSeconds": 638,
          "url": "https://archive.org/download/zen_hi/Zen_hi1.ogg",
          "tags": "zen_hi ",
          "category": "lap_trinh_vien",
          "categoryScore": 4
        },
        {
          "id": "g-studio-1-7-25:G-STUDIO-1-7-25.mp3",
          "identifier": "g-studio-1-7-25",
          "title": "Studio Sound Bath Meditation 1 7 25",
          "creator": "Gordon Rosenberg",
          "durationSeconds": 2306,
          "url": "https://archive.org/download/g-studio-1-7-25/G-STUDIO-1-7-25.mp3",
          "tags": "studio sound bath meditation 1 7 25 gordon rosenberg",
          "category": "lap_trinh_vien",
          "categoryScore": 3
        },
        {
          "id": "gd-studio-4-2-25:GD-STUDIO-4-2-25.mp3",
          "identifier": "gd-studio-4-2-25",
          "title": "Metal Meditation: An Improvisational Studio Sound Bath with Debby and Gordon of Soundwell Boise 4.2.25",
          "creator": "Gordon Rosenberg",
          "durationSeconds": 2204,
          "url": "https://archive.org/download/gd-studio-4-2-25/GD-STUDIO-4-2-25.mp3",
          "tags": "metal meditation: an improvisational studio sound bath with debby and gordon of soundwell boise 4.2.25 gordon rosenberg",
          "category": "lap_trinh_vien",
          "categoryScore": 3
        },
        {
          "id": "sound-bath-gong-10-11-20:SoundBath-Gong-10-11-20.mp3",
          "identifier": "sound-bath-gong-10-11-20",
          "title": "Sound Bath - Heavy Meditation 10-11-20",
          "creator": "Gordon Rosenberg",
          "durationSeconds": 2009,
          "url": "https://archive.org/download/sound-bath-gong-10-11-20/SoundBath-Gong-10-11-20.mp3",
          "tags": "sound bath - heavy meditation 10-11-20 gordon rosenberg",
          "category": "lap_trinh_vien",
          "categoryScore": 3
        },
        {
          "id": "HealingMeditation1:Healing Meditation 1.mp3",
          "identifier": "HealingMeditation1",
          "title": "Healing Meditation 1",
          "creator": "",
          "durationSeconds": 1066,
          "url": "https://archive.org/download/HealingMeditation1/Healing%20Meditation%201.mp3",
          "tags": "healing meditation 1 ",
          "category": "lap_trinh_vien",
          "categoryScore": 3
        },
        {
          "id": "snarky-puppy-bet-empire-central:Zildjian Live! - Larnell Lewis.mp3",
          "identifier": "snarky-puppy-bet-empire-central",
          "title": "Instrumental",
          "creator": "",
          "durationSeconds": 578,
          "url": "https://archive.org/download/snarky-puppy-bet-empire-central/Zildjian%20Live%21%20-%20Larnell%20Lewis.mp3",
          "tags": "instrumental ",
          "category": "lap_trinh_vien",
          "categoryScore": 3
        },
        {
          "id": "AmbientDecay2:08 Futant - Digital Shamanism.mp3",
          "identifier": "AmbientDecay2",
          "title": "(V/A) Ambient Decay 2 ",
          "creator": "Various Artists ",
          "durationSeconds": 557,
          "url": "https://archive.org/download/AmbientDecay2/08%20Futant%20-%20Digital%20Shamanism.mp3",
          "tags": "(v/a) ambient decay 2  various artists ",
          "category": "lap_trinh_vien",
          "categoryScore": 3
        },
        {
          "id": "remix-nin-com-audio-24580:onkodjinn - PNLY (instrumental).mp3",
          "identifier": "remix-nin-com-audio-24580",
          "title": "PNLY (instrumental)",
          "creator": "onkodjinn",
          "durationSeconds": 523,
          "url": "https://archive.org/download/remix-nin-com-audio-24580/onkodjinn%20-%20PNLY%20%28instrumental%29.mp3",
          "tags": "pnly (instrumental) onkodjinn",
          "category": "lap_trinh_vien",
          "categoryScore": 3
        },
        {
          "id": "GuitarInstrumental4:11. TURNING BACK.mp3",
          "identifier": "GuitarInstrumental4",
          "title": "guitar instrumental 4",
          "creator": "",
          "durationSeconds": 517,
          "url": "https://archive.org/download/GuitarInstrumental4/11.%20TURNING%20BACK.mp3",
          "tags": "guitar instrumental 4 ",
          "category": "lap_trinh_vien",
          "categoryScore": 3
        },
        {
          "id": "corvonlordhazethepreventativemeasures:The Corvon H Lordhaze - The Preventative Measures.mp3",
          "identifier": "corvonlordhazethepreventativemeasures",
          "title": "Corvon H Lordhaze - The Preventative Measures (Instrumental)",
          "creator": "The Corvon H Lordhaze",
          "durationSeconds": 436,
          "url": "https://archive.org/download/corvonlordhazethepreventativemeasures/The%20Corvon%20H%20Lordhaze%20-%20The%20Preventative%20Measures.mp3",
          "tags": "corvon h lordhaze - the preventative measures (instrumental) the corvon h lordhaze",
          "category": "lap_trinh_vien",
          "categoryScore": 3
        },
        {
          "id": "TheHandThatRobsTheCradle-instrumentalAccompaniment:TheHandThatRobsTheCradle-Instrumental.mp3",
          "identifier": "TheHandThatRobsTheCradle-instrumentalAccompaniment",
          "title": "The Hand That Robs The Cradle-Instrumental Accompaniment",
          "creator": "Cibeles Jolivette Gonzalez",
          "durationSeconds": 411,
          "url": "https://archive.org/download/TheHandThatRobsTheCradle-instrumentalAccompaniment/TheHandThatRobsTheCradle-Instrumental.mp3",
          "tags": "the hand that robs the cradle-instrumental accompaniment cibeles jolivette gonzalez",
          "category": "lap_trinh_vien",
          "categoryScore": 3
        },
        {
          "id": "GUITARINSTRUMENTAL3:01. DON`T LET THE SUN GO DOWN ON ME - ELTON JOHN.mp3",
          "identifier": "GUITARINSTRUMENTAL3",
          "title": "GUITAR INSTRUMENTAL 3",
          "creator": "",
          "durationSeconds": 410,
          "url": "https://archive.org/download/GUITARINSTRUMENTAL3/01.%20DON%60T%20LET%20THE%20SUN%20GO%20DOWN%20ON%20ME%20-%20ELTON%20JOHN.mp3",
          "tags": "guitar instrumental 3 ",
          "category": "lap_trinh_vien",
          "categoryScore": 3
        },
        {
          "id": "3MonASTUCEPourTRADERPLUSZENMOINSSTRESSE:#3 - Mon ASTUCE pour TRADER PLUS ZEN, MOINS STRESSÉ.mp3",
          "identifier": "3MonASTUCEPourTRADERPLUSZENMOINSSTRESSE",
          "title": "# 3 Mon ASTUCE Pour TRADER PLUS ZEN, MOINS STRESSÉ",
          "creator": "",
          "durationSeconds": 395,
          "url": "https://archive.org/download/3MonASTUCEPourTRADERPLUSZENMOINSSTRESSE/%233%20-%20Mon%20ASTUCE%20pour%20TRADER%20PLUS%20ZEN%2C%20MOINS%20STRESSE%CC%81.mp3",
          "tags": "# 3 mon astuce pour trader plus zen, moins stressé ",
          "category": "lap_trinh_vien",
          "categoryScore": 3
        },
        {
          "id": "remix-nin-com-audio-26084:ConsciousEntityMusic - AATCHB [Conscious Entity Instrumental Cover].mp3",
          "identifier": "remix-nin-com-audio-26084",
          "title": "AATCHB [Conscious Entity Instrumental Cover]",
          "creator": "ConsciousEntityMusic",
          "durationSeconds": 371,
          "url": "https://archive.org/download/remix-nin-com-audio-26084/ConsciousEntityMusic%20-%20AATCHB%20%5BConscious%20Entity%20Instrumental%20Cover%5D.mp3",
          "tags": "aatchb [conscious entity instrumental cover] consciousentitymusic",
          "category": "lap_trinh_vien",
          "categoryScore": 3
        },
        {
          "id": "lp_instrumental-festival-1969_various:disc1/01.12. Junior High Strings - Concertino IN G - Pergolesi, Largo, Allegro.mp3",
          "identifier": "lp_instrumental-festival-1969_various",
          "title": "Instrumental Festival 1969",
          "creator": "Various",
          "durationSeconds": 347,
          "url": "https://archive.org/download/lp_instrumental-festival-1969_various/disc1/01.12.%20Junior%20High%20Strings%20-%20Concertino%20IN%20G%20-%20Pergolesi%2C%20Largo%2C%20Allegro.mp3",
          "tags": "instrumental festival 1969 various",
          "category": "lap_trinh_vien",
          "categoryScore": 3
        },
        {
          "id": "instrumental-guitar-hindi-old-songs:Instrumental/Aaj Purani Raahon Se.MP3",
          "identifier": "instrumental-guitar-hindi-old-songs",
          "title": "Instrumental Guitar Hindi songs",
          "creator": "",
          "durationSeconds": 328,
          "url": "https://archive.org/download/instrumental-guitar-hindi-old-songs/Instrumental/Aaj%20Purani%20Raahon%20Se.MP3",
          "tags": "instrumental guitar hindi songs ",
          "category": "lap_trinh_vien",
          "categoryScore": 3
        },
        {
          "id": "Bandcamp-4262436375:Casual_Sunday_-_BONUS_S_ynchronise_Instrumental-4262436375.mp3",
          "identifier": "Bandcamp-4262436375",
          "title": "Casual Sunday - [BONUS] [S]ynchronise (Instrumental)",
          "creator": "Casual Sunday",
          "durationSeconds": 323,
          "url": "https://archive.org/download/Bandcamp-4262436375/Casual_Sunday_-_BONUS_S_ynchronise_Instrumental-4262436375.mp3",
          "tags": "casual sunday - [bonus] [s]ynchronise (instrumental) casual sunday",
          "category": "lap_trinh_vien",
          "categoryScore": 3
        },
        {
          "id": "1_20250702_20250702_0710:5.mp3",
          "identifier": "1_20250702_20250702_0710",
          "title": "Instrumental Music",
          "creator": "",
          "durationSeconds": 319,
          "url": "https://archive.org/download/1_20250702_20250702_0710/5.mp3",
          "tags": "instrumental music ",
          "category": "lap_trinh_vien",
          "categoryScore": 3
        },
        {
          "id": "no_one_knowsInstrumentalguitarkeys_:nooneknows.mp3",
          "identifier": "no_one_knowsInstrumentalguitarkeys_",
          "title": "no one knows-Instrumental-guitar/keys ",
          "creator": "",
          "durationSeconds": 306,
          "url": "https://archive.org/download/no_one_knowsInstrumentalguitarkeys_/nooneknows.mp3",
          "tags": "no one knows-instrumental-guitar/keys  ",
          "category": "lap_trinh_vien",
          "categoryScore": 3
        },
        {
          "id": "wake_upInstrumentalkeysguitar:instermentaleben.mp3",
          "identifier": "wake_upInstrumentalkeysguitar",
          "title": "wake up-Instrumental-keys/guitar",
          "creator": "",
          "durationSeconds": 290,
          "url": "https://archive.org/download/wake_upInstrumentalkeysguitar/instermentaleben.mp3",
          "tags": "wake up-instrumental-keys/guitar ",
          "category": "lap_trinh_vien",
          "categoryScore": 3
        },
        {
          "id": "nirvana-smells-like-teen-spirit-cover-guitar-instrumental-v2:nirvana-smells-like-teen-spirit-cover-guitar-instrumental-v2.mp3",
          "identifier": "nirvana-smells-like-teen-spirit-cover-guitar-instrumental-v2",
          "title": "nirvana-smells-like-teen-spirit-cover-guitar-instrumental-v2",
          "creator": "",
          "durationSeconds": 289,
          "url": "https://archive.org/download/nirvana-smells-like-teen-spirit-cover-guitar-instrumental-v2/nirvana-smells-like-teen-spirit-cover-guitar-instrumental-v2.mp3",
          "tags": "nirvana-smells-like-teen-spirit-cover-guitar-instrumental-v2 ",
          "category": "lap_trinh_vien",
          "categoryScore": 3
        },
        {
          "id": "acidplanet-audio-00521454:00521454.ogg",
          "identifier": "acidplanet-audio-00521454",
          "title": "RHYME ELEVATION INSTRUMENTAL",
          "creator": "NATHAN NICE PRODUCTIONZ",
          "durationSeconds": 285,
          "url": "https://archive.org/download/acidplanet-audio-00521454/00521454.ogg",
          "tags": "rhyme elevation instrumental nathan nice productionz",
          "category": "lap_trinh_vien",
          "categoryScore": 3
        },
        {
          "id": "rammstein-sonne-instrumental-guitar-cover-by-robert-uludag-commander-fordo:Rammstein - Sonne - (Instrumental) Guitar cover by Robert UludagCommander Fordo.mp3",
          "identifier": "rammstein-sonne-instrumental-guitar-cover-by-robert-uludag-commander-fordo",
          "title": "Rammstein Sonne ( Instrumental) Guitar Cover By Robert Uludag Commander Fordo",
          "creator": "",
          "durationSeconds": 282,
          "url": "https://archive.org/download/rammstein-sonne-instrumental-guitar-cover-by-robert-uludag-commander-fordo/Rammstein%20-%20Sonne%20-%20%28Instrumental%29%20Guitar%20cover%20by%20Robert%20UludagCommander%20Fordo.mp3",
          "tags": "rammstein sonne ( instrumental) guitar cover by robert uludag commander fordo ",
          "category": "lap_trinh_vien",
          "categoryScore": 3
        },
        {
          "id": "the-right-time-instrumental:The Right Time Instrumental.mp3",
          "identifier": "the-right-time-instrumental",
          "title": "The Right Time Instrumental",
          "creator": "LUVIUM, Youth In Circles",
          "durationSeconds": 276,
          "url": "https://archive.org/download/the-right-time-instrumental/The%20Right%20Time%20Instrumental.mp3",
          "tags": "the right time instrumental luvium, youth in circles",
          "category": "lap_trinh_vien",
          "categoryScore": 3
        },
        {
          "id": "04SunFieldsWithLightSynth:04 Sun Fields with light synth.mp3",
          "identifier": "04SunFieldsWithLightSynth",
          "title": "Sun Fields Guitar Instrumental",
          "creator": "Danny Hauger",
          "durationSeconds": 276,
          "url": "https://archive.org/download/04SunFieldsWithLightSynth/04%20Sun%20Fields%20with%20light%20synth.mp3",
          "tags": "sun fields guitar instrumental danny hauger",
          "category": "lap_trinh_vien",
          "categoryScore": 3
        },
        {
          "id": "ERIKDARZELLBLUESBLOW:ERIK DARZELL - \"BLUES BLOW\".mp3",
          "identifier": "ERIKDARZELLBLUESBLOW",
          "title": "ERIK DARZELL  \"THE BLUES BLOW\" Electric Blues Guitar Instrumental ",
          "creator": "E. Darzell",
          "durationSeconds": 274,
          "url": "https://archive.org/download/ERIKDARZELLBLUESBLOW/ERIK%20DARZELL%20-%20%22BLUES%20BLOW%22.mp3",
          "tags": "erik darzell  \"the blues blow\" electric blues guitar instrumental  e. darzell",
          "category": "lap_trinh_vien",
          "categoryScore": 3
        },
        {
          "id": "10IThinkIGuitarInstrumental:10 - I Think I (Guitar Instrumental).ogg",
          "identifier": "10IThinkIGuitarInstrumental",
          "title": "10 I Think I ( Guitar Instrumental)",
          "creator": "oconnerz",
          "durationSeconds": 258,
          "url": "https://archive.org/download/10IThinkIGuitarInstrumental/10%20-%20I%20Think%20I%20%28Guitar%20Instrumental%29.ogg",
          "tags": "10 i think i ( guitar instrumental) oconnerz",
          "category": "lap_trinh_vien",
          "categoryScore": 3
        },
        {
          "id": "TheLivingTombstoneTombstoneRemixes31LoyaltyInstrumental:The Living Tombstone - Tombstone Remixes - 31 Loyalty (Instrumental).mp3",
          "identifier": "TheLivingTombstoneTombstoneRemixes31LoyaltyInstrumental",
          "title": "The Living Tombstone - Tombstone Remixes: [31] Loyalty (Instrumental)",
          "creator": "The Living Tombstone",
          "durationSeconds": 255,
          "url": "https://archive.org/download/TheLivingTombstoneTombstoneRemixes31LoyaltyInstrumental/The%20Living%20Tombstone%20-%20Tombstone%20Remixes%20-%2031%20Loyalty%20%28Instrumental%29.mp3",
          "tags": "the living tombstone - tombstone remixes: [31] loyalty (instrumental) the living tombstone",
          "category": "lap_trinh_vien",
          "categoryScore": 3
        },
        {
          "id": "creep-guitar-instrumental:Creep - Guitar Instrumental.mp3",
          "identifier": "creep-guitar-instrumental",
          "title": "Creep Guitar Instrumental",
          "creator": "",
          "durationSeconds": 253,
          "url": "https://archive.org/download/creep-guitar-instrumental/Creep%20-%20Guitar%20Instrumental.mp3",
          "tags": "creep guitar instrumental ",
          "category": "lap_trinh_vien",
          "categoryScore": 3
        },
        {
          "id": "marcellsiahaanperihinstrumental:Marcell Siahaan - Perih (Instrumental).mp3",
          "identifier": "marcellsiahaanperihinstrumental",
          "title": "Marcell Siahaan Perih ( Instrumental)",
          "creator": "",
          "durationSeconds": 245,
          "url": "https://archive.org/download/marcellsiahaanperihinstrumental/Marcell%20Siahaan%20-%20Perih%20%28Instrumental%29.mp3",
          "tags": "marcell siahaan perih ( instrumental) ",
          "category": "lap_trinh_vien",
          "categoryScore": 3
        },
        {
          "id": "acnr-soundtrack-kk-instrumental:Disc 3/21. Marine Song 2001.mp3",
          "identifier": "acnr-soundtrack-kk-instrumental",
          "title": "Animal Crossing: New Horizons Original Soundtrack K.K. Slider Music Collection Instrumental",
          "creator": "K.K. Slider Kazumi Totaka",
          "durationSeconds": 241,
          "url": "https://archive.org/download/acnr-soundtrack-kk-instrumental/Disc%203/21.%20Marine%20Song%202001.mp3",
          "tags": "animal crossing: new horizons original soundtrack k.k. slider music collection instrumental k.k. slider kazumi totaka",
          "category": "lap_trinh_vien",
          "categoryScore": 3
        },
        {
          "id": "acidplanet-audio-01041177:01041177.ogg",
          "identifier": "acidplanet-audio-01041177",
          "title": "A Space Age Love - Instrumental",
          "creator": "AMYGDALA",
          "durationSeconds": 239,
          "url": "https://archive.org/download/acidplanet-audio-01041177/01041177.ogg",
          "tags": "a space age love - instrumental amygdala",
          "category": "lap_trinh_vien",
          "categoryScore": 3
        },
        {
          "id": "slippy-blosso-horizon-back-to-life-official-instrumental:Slippy & Blosso - Horizon (Back To Life) [Official Instrumental].mp3",
          "identifier": "slippy-blosso-horizon-back-to-life-official-instrumental",
          "title": "Slippy & Blosso Horizon ( Back To Life) [ Official Instrumental]",
          "creator": "",
          "durationSeconds": 239,
          "url": "https://archive.org/download/slippy-blosso-horizon-back-to-life-official-instrumental/Slippy%20%26%20Blosso%20-%20Horizon%20%28Back%20To%20Life%29%20%5BOfficial%20Instrumental%5D.mp3",
          "tags": "slippy & blosso horizon ( back to life) [ official instrumental] ",
          "category": "lap_trinh_vien",
          "categoryScore": 3
        },
        {
          "id": "y-2mate.com-aaoge-jab-tum-saajna-jab-we-met-hindi-flute-cover-hd-instrumental-song-kedarnath-bailur:y2mate.com - Aaoge Jab Tum Saajna  Jab We Met  Hindi Flute Cover  HD  Instrumental Song  Kedarnath Bailur.mp3",
          "identifier": "y-2mate.com-aaoge-jab-tum-saajna-jab-we-met-hindi-flute-cover-hd-instrumental-song-kedarnath-bailur",
          "title": "Y 2mate.com Aaoge Jab Tum Saajna Jab We Met Hindi Flute Cover HD Instrumental Song Kedarnath Bailur",
          "creator": "",
          "durationSeconds": 236,
          "url": "https://archive.org/download/y-2mate.com-aaoge-jab-tum-saajna-jab-we-met-hindi-flute-cover-hd-instrumental-song-kedarnath-bailur/y2mate.com%20-%20Aaoge%20Jab%20Tum%20Saajna%20%20Jab%20We%20Met%20%20Hindi%20Flute%20Cover%20%20HD%20%20Instrumental%20Song%20%20Kedarnath%20Bailur.mp3",
          "tags": "y 2mate.com aaoge jab tum saajna jab we met hindi flute cover hd instrumental song kedarnath bailur ",
          "category": "lap_trinh_vien",
          "categoryScore": 3
        },
        {
          "id": "ThirdDay-HowGreatThouArtacousticGuitarInstrumental:ThirdDay-HowGreatThouArtacousticGuitarInstrumental.mp3",
          "identifier": "ThirdDay-HowGreatThouArtacousticGuitarInstrumental",
          "title": "Third Day - How Great Thou Art (acoustic guitar instrumental)",
          "creator": "",
          "durationSeconds": 232,
          "url": "https://archive.org/download/ThirdDay-HowGreatThouArtacousticGuitarInstrumental/ThirdDay-HowGreatThouArtacousticGuitarInstrumental.mp3",
          "tags": "third day - how great thou art (acoustic guitar instrumental) ",
          "category": "lap_trinh_vien",
          "categoryScore": 3
        },
        {
          "id": "reekadobanksrorainstrumental:Reekado_Banks_-_Rora_Instrumental.mp3",
          "identifier": "reekadobanksrorainstrumental",
          "title": "Reekado Banks Rora Instrumental",
          "creator": "",
          "durationSeconds": 231,
          "url": "https://archive.org/download/reekadobanksrorainstrumental/Reekado_Banks_-_Rora_Instrumental.mp3",
          "tags": "reekado banks rora instrumental ",
          "category": "lap_trinh_vien",
          "categoryScore": 3
        },
        {
          "id": "2BabaFrenemiesFtWajeINSTRUMENTALViaInstrumentals:2Baba-Frenemies-ft-Waje INSTRUMENTAL via instrumentals.mp3",
          "identifier": "2BabaFrenemiesFtWajeINSTRUMENTALViaInstrumentals",
          "title": "2 Baba Frenemies Ft Waje INSTRUMENTAL Via Instrumentals",
          "creator": "",
          "durationSeconds": 230,
          "url": "https://archive.org/download/2BabaFrenemiesFtWajeINSTRUMENTALViaInstrumentals/2Baba-Frenemies-ft-Waje%20INSTRUMENTAL%20via%20instrumentals.mp3",
          "tags": "2 baba frenemies ft waje instrumental via instrumentals ",
          "category": "lap_trinh_vien",
          "categoryScore": 3
        },
        {
          "id": "eternityinstrumental:Eternity Instrumental.mp3",
          "identifier": "eternityinstrumental",
          "title": "Eternity Instrumental",
          "creator": "AJ Stoan",
          "durationSeconds": 225,
          "url": "https://archive.org/download/eternityinstrumental/Eternity%20Instrumental.mp3",
          "tags": "eternity instrumental aj stoan",
          "category": "lap_trinh_vien",
          "categoryScore": 3
        },
        {
          "id": "musica-bosque-magico-instrumental-musica-instrumental-relajante:Música Bosque Mágico InstrumentalMúsica instrumental relajante.mp3",
          "identifier": "musica-bosque-magico-instrumental-musica-instrumental-relajante",
          "title": "Música Bosque Mágico Instrumental Música Instrumental Relajante",
          "creator": "",
          "durationSeconds": 224,
          "url": "https://archive.org/download/musica-bosque-magico-instrumental-musica-instrumental-relajante/M%C3%BAsica%20Bosque%20M%C3%A1gico%20InstrumentalM%C3%BAsica%20instrumental%20relajante.mp3",
          "tags": "música bosque mágico instrumental música instrumental relajante ",
          "category": "lap_trinh_vien",
          "categoryScore": 3
        },
        {
          "id": "acidplanet-audio-01057990:01057990.ogg",
          "identifier": "acidplanet-audio-01057990",
          "title": "the call of death (instrumental)",
          "creator": "INCREDIBLE RYK",
          "durationSeconds": 215,
          "url": "https://archive.org/download/acidplanet-audio-01057990/01057990.ogg",
          "tags": "the call of death (instrumental) incredible ryk",
          "category": "lap_trinh_vien",
          "categoryScore": 3
        },
        {
          "id": "Djjes-athTheEndtheGuitarinstrumental:Djjes-athTheAndtheGituar.mp3",
          "identifier": "Djjes-athTheEndtheGuitarinstrumental",
          "title": "DJJES-Ath The End (The Guitar) [Instrumental]",
          "creator": "Djjes; Jehoschua Saalfeld",
          "durationSeconds": 215,
          "url": "https://archive.org/download/Djjes-athTheEndtheGuitarinstrumental/Djjes-athTheAndtheGituar.mp3",
          "tags": "djjes-ath the end (the guitar) [instrumental] djjes; jehoschua saalfeld",
          "category": "lap_trinh_vien",
          "categoryScore": 3
        },
        {
          "id": "TwoStepsFromHellStrengthOfAThousandMenInstrumentalCoreRemix:Two Steps From Hell - Strength Of A Thousand Men [Instrumental Core Remix].mp3",
          "identifier": "TwoStepsFromHellStrengthOfAThousandMenInstrumentalCoreRemix",
          "title": "Two Steps From Hell Strength Of A Thousand Men [ Instrumental Core Remix]",
          "creator": "",
          "durationSeconds": 213,
          "url": "https://archive.org/download/TwoStepsFromHellStrengthOfAThousandMenInstrumentalCoreRemix/Two%20Steps%20From%20Hell%20-%20Strength%20Of%20A%20Thousand%20Men%20%5BInstrumental%20Core%20Remix%5D.mp3",
          "tags": "two steps from hell strength of a thousand men [ instrumental core remix] ",
          "category": "lap_trinh_vien",
          "categoryScore": 3
        },
        {
          "id": "LastGoodbyeinstrumental-DiaforaguitarOnly:AcousticSongcompleteGuitar.mp3",
          "identifier": "LastGoodbyeinstrumental-DiaforaguitarOnly",
          "title": "Last goodbye (instrumental - Diafora (guitar only)",
          "creator": "",
          "durationSeconds": 213,
          "url": "https://archive.org/download/LastGoodbyeinstrumental-DiaforaguitarOnly/AcousticSongcompleteGuitar.mp3",
          "tags": "last goodbye (instrumental - diafora (guitar only) ",
          "category": "lap_trinh_vien",
          "categoryScore": 3
        },
        {
          "id": "nckgr:[FREE] Acoustic Guitar Instrumental Beat 2020 #3 (For Singing and Rapping) [YTmp3.net].mp3",
          "identifier": "nckgr",
          "title": "[ FREE] Acoustic Guitar Instrumental Beat 2020 # 3 ( For Singing And Rapping) [ YTmp 3.net]",
          "creator": "",
          "durationSeconds": 212,
          "url": "https://archive.org/download/nckgr/%5BFREE%5D%20Acoustic%20Guitar%20Instrumental%20Beat%202020%20%233%20%28For%20Singing%20and%20Rapping%29%20%5BYTmp3.net%5D.mp3",
          "tags": "[ free] acoustic guitar instrumental beat 2020 # 3 ( for singing and rapping) [ ytmp 3.net] ",
          "category": "lap_trinh_vien",
          "categoryScore": 3
        },
        {
          "id": "the-greatest-from-sia-instrumental-version:The Greatest from Sia (Instrumental Version).mp3",
          "identifier": "the-greatest-from-sia-instrumental-version",
          "title": "The Greatest From Sia (Instrumental Version)",
          "creator": "",
          "durationSeconds": 211,
          "url": "https://archive.org/download/the-greatest-from-sia-instrumental-version/The%20Greatest%20from%20Sia%20%28Instrumental%20Version%29.mp3",
          "tags": "the greatest from sia (instrumental version) ",
          "category": "lap_trinh_vien",
          "categoryScore": 3
        },
        {
          "id": "soundcloud-346182007:Fairlight (Instrumental)-346182007.mp3",
          "identifier": "soundcloud-346182007",
          "title": "Fairlight (Instrumental)",
          "creator": "Discoholic",
          "durationSeconds": 210,
          "url": "https://archive.org/download/soundcloud-346182007/Fairlight%20%28Instrumental%29-346182007.mp3",
          "tags": "fairlight (instrumental) discoholic",
          "category": "lap_trinh_vien",
          "categoryScore": 3
        },
        {
          "id": "clu4vmnrju64gfpp-lurraren-eguna-ospatu-zen-igandean-beran:Lurraren eguna ospatu zen igandean Beran - #0.mp3",
          "identifier": "clu4vmnrju64gfpp-lurraren-eguna-ospatu-zen-igandean-beran",
          "title": "Lurraren eguna ospatu zen igandean Beran",
          "creator": "Antxeta Irratia",
          "durationSeconds": 209,
          "url": "https://archive.org/download/clu4vmnrju64gfpp-lurraren-eguna-ospatu-zen-igandean-beran/Lurraren%20eguna%20ospatu%20zen%20igandean%20Beran%20-%20%230.mp3",
          "tags": "lurraren eguna ospatu zen igandean beran antxeta irratia",
          "category": "lap_trinh_vien",
          "categoryScore": 3
        },
        {
          "id": "acidplanet-audio-01478959:01478959.mp3",
          "identifier": "acidplanet-audio-01478959",
          "title": "Ambient Moon - Steng",
          "creator": "John Stenger",
          "durationSeconds": 208,
          "url": "https://archive.org/download/acidplanet-audio-01478959/01478959.mp3",
          "tags": "ambient moon - steng john stenger",
          "category": "lap_trinh_vien",
          "categoryScore": 3
        },
        {
          "id": "rainbows-blood-instrumental:Rainbows Blood - Instrumental.mp3",
          "identifier": "rainbows-blood-instrumental",
          "title": "Rainbows Blood Instrumental",
          "creator": "Interrobang Pie",
          "durationSeconds": 208,
          "url": "https://archive.org/download/rainbows-blood-instrumental/Rainbows%20Blood%20-%20Instrumental.mp3",
          "tags": "rainbows blood instrumental interrobang pie",
          "category": "lap_trinh_vien",
          "categoryScore": 3
        },
        {
          "id": "thank-u-next-from-ariana-grande-instrumental-version:Thank U, Next from Ariana Grande (Instrumental Version).mp3",
          "identifier": "thank-u-next-from-ariana-grande-instrumental-version",
          "title": "Thank U, Next From Ariana Grande (Instrumental Version)",
          "creator": "",
          "durationSeconds": 208,
          "url": "https://archive.org/download/thank-u-next-from-ariana-grande-instrumental-version/Thank%20U%2C%20Next%20from%20Ariana%20Grande%20%28Instrumental%20Version%29.mp3",
          "tags": "thank u, next from ariana grande (instrumental version) ",
          "category": "lap_trinh_vien",
          "categoryScore": 3
        },
        {
          "id": "freegambixoffsettypebeatsmokeguitarrapinstrumental2019:[FREE] Gambi x Offset Type Beat - Smoke Guitar Rap Instrumental 2019.mp3",
          "identifier": "freegambixoffsettypebeatsmokeguitarrapinstrumental2019",
          "title": "[ FREE] Gambi X Offset Type Beat Smoke Guitar Rap Instrumental 2019",
          "creator": "",
          "durationSeconds": 207,
          "url": "https://archive.org/download/freegambixoffsettypebeatsmokeguitarrapinstrumental2019/%5BFREE%5D%20Gambi%20x%20Offset%20Type%20Beat%20-%20Smoke%20Guitar%20Rap%20Instrumental%202019.mp3",
          "tags": "[ free] gambi x offset type beat smoke guitar rap instrumental 2019 ",
          "category": "lap_trinh_vien",
          "categoryScore": 3
        },
        {
          "id": "te-dominar-from-daya-luz-instrumental-version:Te Dominar from Daya Luz (Instrumental Version).mp3",
          "identifier": "te-dominar-from-daya-luz-instrumental-version",
          "title": "Te Dominar From Daya Luz (Instrumental Version)",
          "creator": "",
          "durationSeconds": 206,
          "url": "https://archive.org/download/te-dominar-from-daya-luz-instrumental-version/Te%20Dominar%20from%20Daya%20Luz%20%28Instrumental%20Version%29.mp3",
          "tags": "te dominar from daya luz (instrumental version) ",
          "category": "lap_trinh_vien",
          "categoryScore": 3
        },
        {
          "id": "KhalidTalkInstrumentalViaInstrumentals.com.ng:Khalid - Talk Instrumental via instrumentals.com.ng.mp3",
          "identifier": "KhalidTalkInstrumentalViaInstrumentals.com.ng",
          "title": "Khalid Talk Instrumental Via Instrumentals.com.ng",
          "creator": "",
          "durationSeconds": 200,
          "url": "https://archive.org/download/KhalidTalkInstrumentalViaInstrumentals.com.ng/Khalid%20-%20Talk%20Instrumental%20via%20instrumentals.com.ng.mp3",
          "tags": "khalid talk instrumental via instrumentals.com.ng ",
          "category": "lap_trinh_vien",
          "categoryScore": 3
        },
        {
          "id": "remix-nin-com-audio-07360:EVILE4EVA - The Great Destroyer Instrumental (Eliminator Will Kill Your Ass Mix By Evil E).mp3",
          "identifier": "remix-nin-com-audio-07360",
          "title": "The Great Destroyer Instrumental (Eliminator Will Kill Your Ass Mix By Evil E)",
          "creator": "EVILE4EVA",
          "durationSeconds": 199,
          "url": "https://archive.org/download/remix-nin-com-audio-07360/EVILE4EVA%20-%20The%20Great%20Destroyer%20Instrumental%20%28Eliminator%20Will%20Kill%20Your%20Ass%20Mix%20By%20Evil%20E%29.mp3",
          "tags": "the great destroyer instrumental (eliminator will kill your ass mix by evil e) evile4eva",
          "category": "lap_trinh_vien",
          "categoryScore": 3
        },
        {
          "id": "remix-nin-com-audio-21122:Dahak - The Aftermath (Instrumental).mp3",
          "identifier": "remix-nin-com-audio-21122",
          "title": "The Aftermath (Instrumental)",
          "creator": "Dahak",
          "durationSeconds": 199,
          "url": "https://archive.org/download/remix-nin-com-audio-21122/Dahak%20-%20The%20Aftermath%20%28Instrumental%29.mp3",
          "tags": "the aftermath (instrumental) dahak",
          "category": "lap_trinh_vien",
          "categoryScore": 3
        },
        {
          "id": "talk-from-khalid-instrumental-version:Talk from Khalid (Instrumental Version).mp3",
          "identifier": "talk-from-khalid-instrumental-version",
          "title": "Talk From Khalid (Instrumental Version)",
          "creator": "",
          "durationSeconds": 198,
          "url": "https://archive.org/download/talk-from-khalid-instrumental-version/Talk%20from%20Khalid%20%28Instrumental%20Version%29.mp3",
          "tags": "talk from khalid (instrumental version) ",
          "category": "lap_trinh_vien",
          "categoryScore": 3
        },
        {
          "id": "slowmotionterrahbatrossftmiragadsgdancehallafrobeatinstrumental:Wine Up Riddim (Dancehall - Moombahton Afro Beat Instrumental) 2019 - Alann Ulises (192  kbps) (LoadMp4.Com).mp3",
          "identifier": "slowmotionterrahbatrossftmiragadsgdancehallafrobeatinstrumental",
          "title": "Slow motion Terrah batross ft Miraga dsg ( Dancehall Afro Beat Instrumental) 2019",
          "creator": "Miraga DSg",
          "durationSeconds": 197,
          "url": "https://archive.org/download/slowmotionterrahbatrossftmiragadsgdancehallafrobeatinstrumental/Wine%20Up%20Riddim%20%28Dancehall%20-%20Moombahton%20Afro%20Beat%20Instrumental%29%202019%20-%20Alann%20Ulises%20%28192%20%20kbps%29%20%28LoadMp4.Com%29.mp3",
          "tags": "slow motion terrah batross ft miraga dsg ( dancehall afro beat instrumental) 2019 miraga dsg",
          "category": "lap_trinh_vien",
          "categoryScore": 3
        },
        {
          "id": "tvtunes_22951:Uta no Prince-sama - Over the Rainbow - Instrumental.mp3",
          "identifier": "tvtunes_22951",
          "title": "Uta no Prince-sama - Over the Rainbow - Instrumental - Theme Song",
          "creator": "",
          "durationSeconds": 194,
          "url": "https://archive.org/download/tvtunes_22951/Uta%20no%20Prince-sama%20-%20Over%20the%20Rainbow%20-%20Instrumental.mp3",
          "tags": "uta no prince-sama - over the rainbow - instrumental - theme song ",
          "category": "lap_trinh_vien",
          "categoryScore": 3
        },
        {
          "id": "690801c-because-take-1-instrumental:690801c Because (take 1 instrumental).mp3",
          "identifier": "690801c-because-take-1-instrumental",
          "title": "690801c Because (take 1 Instrumental)",
          "creator": "",
          "durationSeconds": 188,
          "url": "https://archive.org/download/690801c-because-take-1-instrumental/690801c%20Because%20%28take%201%20instrumental%29.mp3",
          "tags": "690801c because (take 1 instrumental) ",
          "category": "lap_trinh_vien",
          "categoryScore": 3
        },
        {
          "id": "AmbientCircus:AmbientCircus.ogg",
          "identifier": "AmbientCircus",
          "title": "Ambient Circus",
          "creator": "Luke Van Patten",
          "durationSeconds": 187,
          "url": "https://archive.org/download/AmbientCircus/AmbientCircus.ogg",
          "tags": "ambient circus luke van patten",
          "category": "lap_trinh_vien",
          "categoryScore": 3
        },
        {
          "id": "q-50-wlil-50-x-fully-chop-bounce-out-instrumental-prod.by.-yamaica:Q50WLIL50 x FullyChop - Bounce Out (Instrumental) (Prod.by.Yamaica).mp3",
          "identifier": "q-50-wlil-50-x-fully-chop-bounce-out-instrumental-prod.by.-yamaica",
          "title": "Q 50 WLIL 50 X Fully Chop Bounce Out ( Instrumental) ( Prod.by. Yamaica)",
          "creator": "",
          "durationSeconds": 183,
          "url": "https://archive.org/download/q-50-wlil-50-x-fully-chop-bounce-out-instrumental-prod.by.-yamaica/Q50WLIL50%20x%20FullyChop%20-%20Bounce%20Out%20%28Instrumental%29%20%28Prod.by.Yamaica%29.mp3",
          "tags": "q 50 wlil 50 x fully chop bounce out ( instrumental) ( prod.by. yamaica) ",
          "category": "lap_trinh_vien",
          "categoryScore": 3
        }
      ]
    },
    "ke_toan": {
      "label": "Ke toan - On dinh va chi tiet",
      "description": "Tiet tau deu, giam met khi xu ly so lieu",
      "tracks": [
        {
          "id": "30-minute-flute-music-calm-music-meditation-music-insomnia-relax-study-sleep-music:Amazing 30 min Krishna Flute Music   RELAXING Meditation Music For BODY AND SOUL.mp3",
          "identifier": "30-minute-flute-music-calm-music-meditation-music-insomnia-relax-study-sleep-music",
          "title": "🟢 30 Minute Flute Music, Calm Music, Meditation Music, Insomnia, Relax, Study, Sleep Music",
          "creator": "",
          "durationSeconds": 1959,
          "url": "https://archive.org/download/30-minute-flute-music-calm-music-meditation-music-insomnia-relax-study-sleep-music/Amazing%2030%20min%20Krishna%20Flute%20Music%20%20%20RELAXING%20Meditation%20Music%20For%20BODY%20AND%20SOUL.mp3",
          "tags": "🟢 30 minute flute music, calm music, meditation music, insomnia, relax, study, sleep music ",
          "category": "ke_toan",
          "categoryScore": 7
        },
        {
          "id": "bossa-nova-piano-instrumental-mp3:bossa-nova-piano-instrumental-mp3.mp3",
          "identifier": "bossa-nova-piano-instrumental-mp3",
          "title": "Bossa Nova Piano Instrumental - Brasil",
          "creator": "Musicalmix",
          "durationSeconds": 308,
          "url": "https://archive.org/download/bossa-nova-piano-instrumental-mp3/bossa-nova-piano-instrumental-mp3.mp3",
          "tags": "bossa nova piano instrumental - brasil musicalmix",
          "category": "ke_toan",
          "categoryScore": 7
        },
        {
          "id": "RelaxMusicGuitarSoftPianoInstrumental2:relax music - guitar soft - piano - instrumental(2).mp3",
          "identifier": "RelaxMusicGuitarSoftPianoInstrumental2",
          "title": "Relax Music Guitar Soft Piano Instrumental( 2)",
          "creator": "me",
          "durationSeconds": 217,
          "url": "https://archive.org/download/RelaxMusicGuitarSoftPianoInstrumental2/relax%20music%20-%20guitar%20soft%20-%20piano%20-%20instrumental%282%29.mp3",
          "tags": "relax music guitar soft piano instrumental( 2) me",
          "category": "ke_toan",
          "categoryScore": 7
        },
        {
          "id": "RayWSmithPianoInstrumentalMajic:Ray W Smith Piano Instrumental majic.mp3",
          "identifier": "RayWSmithPianoInstrumentalMajic",
          "title": "Ray W Smith Piano Instrumental Majic",
          "creator": "Ray W Smith",
          "durationSeconds": 1878,
          "url": "https://archive.org/download/RayWSmithPianoInstrumentalMajic/Ray%20W%20Smith%20Piano%20Instrumental%20majic.mp3",
          "tags": "ray w smith piano instrumental majic ray w smith",
          "category": "ke_toan",
          "categoryScore": 6
        },
        {
          "id": "la-magia-del-piano-musica-instrumental-de-piano-musica-hermosa-y-relajante_20251031.mp3:La Magia del Piano  (Música  Instrumental de Piano, Música hermosa y relajante).mp3",
          "identifier": "la-magia-del-piano-musica-instrumental-de-piano-musica-hermosa-y-relajante_20251031.mp3",
          "title": "La Magia Del Piano ( Música Instrumental De Piano, Música Hermosa Y Relajante)",
          "creator": "",
          "durationSeconds": 827,
          "url": "https://archive.org/download/la-magia-del-piano-musica-instrumental-de-piano-musica-hermosa-y-relajante_20251031.mp3/La%20Magia%20del%20Piano%20%20%28M%C3%BAsica%20%20Instrumental%20de%20Piano%2C%20M%C3%BAsica%20hermosa%20y%20relajante%29.mp3",
          "tags": "la magia del piano ( música instrumental de piano, música hermosa y relajante) ",
          "category": "ke_toan",
          "categoryScore": 6
        },
        {
          "id": "la-magia-del-piano-musica-instrumental-de-piano-musica-hermosa-y-relajante_202510:La Magia del Piano  (Música  Instrumental de Piano, Música hermosa y relajante).mp3",
          "identifier": "la-magia-del-piano-musica-instrumental-de-piano-musica-hermosa-y-relajante_202510",
          "title": "La Magia Del Piano ( Música Instrumental De Piano, Música Hermosa Y Relajante)",
          "creator": "",
          "durationSeconds": 827,
          "url": "https://archive.org/download/la-magia-del-piano-musica-instrumental-de-piano-musica-hermosa-y-relajante_202510/La%20Magia%20del%20Piano%20%20%28M%C3%BAsica%20%20Instrumental%20de%20Piano%2C%20M%C3%BAsica%20hermosa%20y%20relajante%29.mp3",
          "tags": "la magia del piano ( música instrumental de piano, música hermosa y relajante) ",
          "category": "ke_toan",
          "categoryScore": 6
        },
        {
          "id": "3-min-piano-music-quick-positive-energy-meditation-3-min-relaxing-piano-music-relaxation-music:3 Min Piano Music, Quick Positive Energy Meditation, 3 Min Relaxing Piano Music, Relaxation Music.mp3",
          "identifier": "3-min-piano-music-quick-positive-energy-meditation-3-min-relaxing-piano-music-relaxation-music",
          "title": "3 Min Piano Music, Quick Positive Energy Meditation, 3 Min Relaxing Piano Music, Relaxation Music",
          "creator": "",
          "durationSeconds": 184,
          "url": "https://archive.org/download/3-min-piano-music-quick-positive-energy-meditation-3-min-relaxing-piano-music-relaxation-music/3%20Min%20Piano%20Music%2C%20Quick%20Positive%20Energy%20Meditation%2C%203%20Min%20Relaxing%20Piano%20Music%2C%20Relaxation%20Music.mp3",
          "tags": "3 min piano music, quick positive energy meditation, 3 min relaxing piano music, relaxation music ",
          "category": "ke_toan",
          "categoryScore": 6
        },
        {
          "id": "piano_meditation:piano_meditation.mp3",
          "identifier": "piano_meditation",
          "title": "piano_meditation",
          "creator": "",
          "durationSeconds": 2028,
          "url": "https://archive.org/download/piano_meditation/piano_meditation.mp3",
          "tags": "piano_meditation ",
          "category": "ke_toan",
          "categoryScore": 5
        },
        {
          "id": "gentle-piano-meditation-9692:gentle-piano-meditation-9692.mp3",
          "identifier": "gentle-piano-meditation-9692",
          "title": "gentle-piano-meditation-9692",
          "creator": "",
          "durationSeconds": 920,
          "url": "https://archive.org/download/gentle-piano-meditation-9692/gentle-piano-meditation-9692.mp3",
          "tags": "gentle-piano-meditation-9692 ",
          "category": "ke_toan",
          "categoryScore": 5
        },
        {
          "id": "SoothingPianoMusicForMeditation:Soothing Piano Music For Meditation.mp3",
          "identifier": "SoothingPianoMusicForMeditation",
          "title": "Soothing Piano Music For Meditation",
          "creator": "",
          "durationSeconds": 907,
          "url": "https://archive.org/download/SoothingPianoMusicForMeditation/Soothing%20Piano%20Music%20For%20Meditation.mp3",
          "tags": "soothing piano music for meditation ",
          "category": "ke_toan",
          "categoryScore": 5
        },
        {
          "id": "20250610161354-bisaya-ang-plano-sa-mga-bgm-piano-dreamcloud-meditation-179215-leigh-robinson-from:20250610161354 __ Bisaya ANG PLANO SA MGA - BGM piano dreamcloud meditation 179215 Leigh Robinson from.mp3",
          "identifier": "20250610161354-bisaya-ang-plano-sa-mga-bgm-piano-dreamcloud-meditation-179215-leigh-robinson-from",
          "title": "20250610161354 Bisaya ANG PLANO SA MGA BGM Piano Dreamcloud Meditation 179215 Leigh Robinson From",
          "creator": "Justice4Adri",
          "durationSeconds": 816,
          "url": "https://archive.org/download/20250610161354-bisaya-ang-plano-sa-mga-bgm-piano-dreamcloud-meditation-179215-leigh-robinson-from/20250610161354%20__%20Bisaya%20ANG%20PLANO%20SA%20MGA%20-%20BGM%20piano%20dreamcloud%20meditation%20179215%20Leigh%20Robinson%20from.mp3",
          "tags": "20250610161354 bisaya ang plano sa mga bgm piano dreamcloud meditation 179215 leigh robinson from justice4adri",
          "category": "ke_toan",
          "categoryScore": 5
        },
        {
          "id": "20250610173530-english-the-degillo-s-plan-to-erase-me-bgm-piano-dreamcloud-medit:20250610173530 🇺🇸 English - THE DEGILLO_S PLAN TO ERASE ME - BGM piano dreamcloud meditation 179215 Leigh Robinson from.mp3",
          "identifier": "20250610173530-english-the-degillo-s-plan-to-erase-me-bgm-piano-dreamcloud-medit",
          "title": "20250610173530 🇺🇸 English THE DEGILLO S PLAN TO ERASE ME BGM Piano Dreamcloud Meditation 179215 Leigh Robinson From",
          "creator": "Justice4Adri",
          "durationSeconds": 734,
          "url": "https://archive.org/download/20250610173530-english-the-degillo-s-plan-to-erase-me-bgm-piano-dreamcloud-medit/20250610173530%20%F0%9F%87%BA%F0%9F%87%B8%20English%20-%20THE%20DEGILLO_S%20PLAN%20TO%20ERASE%20ME%20-%20BGM%20piano%20dreamcloud%20meditation%20179215%20Leigh%20Robinson%20from.mp3",
          "tags": "20250610173530 🇺🇸 english the degillo s plan to erase me bgm piano dreamcloud meditation 179215 leigh robinson from justice4adri",
          "category": "ke_toan",
          "categoryScore": 5
        },
        {
          "id": "goodness-of-god-by-bethel-music-piano-instrumental_202410:Goodness of God by Bethel Music (Piano Instrumental).mp3",
          "identifier": "goodness-of-god-by-bethel-music-piano-instrumental_202410",
          "title": "Goodness Of God By Bethel Music ( Piano Instrumental)",
          "creator": "sekoya",
          "durationSeconds": 544,
          "url": "https://archive.org/download/goodness-of-god-by-bethel-music-piano-instrumental_202410/Goodness%20of%20God%20by%20Bethel%20Music%20%28Piano%20Instrumental%29.mp3",
          "tags": "goodness of god by bethel music ( piano instrumental) sekoya",
          "category": "ke_toan",
          "categoryScore": 5
        },
        {
          "id": "Instrumental_Song_Healing.mp3:Goodness of God by Bethel Music (Piano Instrumental)(1).mp3",
          "identifier": "Instrumental_Song_Healing.mp3",
          "title": "Goodness Of God By Bethel Music ( Piano Instrumental)( 1)",
          "creator": "",
          "durationSeconds": 544,
          "url": "https://archive.org/download/Instrumental_Song_Healing.mp3/Goodness%20of%20God%20by%20Bethel%20Music%20%28Piano%20Instrumental%29%281%29.mp3",
          "tags": "goodness of god by bethel music ( piano instrumental)( 1) ",
          "category": "ke_toan",
          "categoryScore": 5
        },
        {
          "id": "goodness-of-god-by-bethel-music-piano-instrumental:Goodness of God by Bethel Music (Piano Instrumental).mp3",
          "identifier": "goodness-of-god-by-bethel-music-piano-instrumental",
          "title": "Goodness Of God By Bethel Music ( Piano Instrumental)",
          "creator": "",
          "durationSeconds": 544,
          "url": "https://archive.org/download/goodness-of-god-by-bethel-music-piano-instrumental/Goodness%20of%20God%20by%20Bethel%20Music%20%28Piano%20Instrumental%29.mp3",
          "tags": "goodness of god by bethel music ( piano instrumental) ",
          "category": "ke_toan",
          "categoryScore": 5
        },
        {
          "id": "instrumental-piano-rohani-kristen-4:Instrumental Piano Rohani Kristen 4.mp3",
          "identifier": "instrumental-piano-rohani-kristen-4",
          "title": "Instrumental Piano Rohani Kristen",
          "creator": "",
          "durationSeconds": 540,
          "url": "https://archive.org/download/instrumental-piano-rohani-kristen-4/Instrumental%20Piano%20Rohani%20Kristen%204.mp3",
          "tags": "instrumental piano rohani kristen ",
          "category": "ke_toan",
          "categoryScore": 5
        },
        {
          "id": "remix-nin-com-audio-20647:echoesofsilence - Something I Can Never Have [Piano Instrumental].mp3",
          "identifier": "remix-nin-com-audio-20647",
          "title": "Something I Can Never Have [Piano Instrumental]",
          "creator": "echoesofsilence",
          "durationSeconds": 415,
          "url": "https://archive.org/download/remix-nin-com-audio-20647/echoesofsilence%20-%20Something%20I%20Can%20Never%20Have%20%5BPiano%20Instrumental%5D.mp3",
          "tags": "something i can never have [piano instrumental] echoesofsilence",
          "category": "ke_toan",
          "categoryScore": 5
        },
        {
          "id": "remix-nin-com-audio-12557:ninima - Something I Can Never Have (Instrumental Cover, Featuring Piano) - NINIMA.mp3",
          "identifier": "remix-nin-com-audio-12557",
          "title": "Something I Can Never Have (Instrumental Cover, Featuring Piano) - NINIMA",
          "creator": "ninima",
          "durationSeconds": 373,
          "url": "https://archive.org/download/remix-nin-com-audio-12557/ninima%20-%20Something%20I%20Can%20Never%20Have%20%28Instrumental%20Cover%2C%20Featuring%20Piano%29%20-%20NINIMA.mp3",
          "tags": "something i can never have (instrumental cover, featuring piano) - ninima ninima",
          "category": "ke_toan",
          "categoryScore": 5
        },
        {
          "id": "yeshua-instrumental-piano:yeshua-instrumental-piano.mp3",
          "identifier": "yeshua-instrumental-piano",
          "title": "yeshua-instrumental-piano",
          "creator": "",
          "durationSeconds": 350,
          "url": "https://archive.org/download/yeshua-instrumental-piano/yeshua-instrumental-piano.mp3",
          "tags": "yeshua-instrumental-piano ",
          "category": "ke_toan",
          "categoryScore": 5
        },
        {
          "id": "remix-nin-com-audio-15526:vikatine - We're In This Together - piano instrumental.mp3",
          "identifier": "remix-nin-com-audio-15526",
          "title": "We're In This Together - piano instrumental",
          "creator": "vikatine",
          "durationSeconds": 326,
          "url": "https://archive.org/download/remix-nin-com-audio-15526/vikatine%20-%20We%27re%20In%20This%20Together%20-%20piano%20instrumental.mp3",
          "tags": "we're in this together - piano instrumental vikatine",
          "category": "ke_toan",
          "categoryScore": 5
        },
        {
          "id": "JeremySouleFearNotThisNightPianoCoverInstrumentalGuildWars2OST:Jeremy Soule - Fear Not This Night -Piano Cover Instrumental (Guild Wars 2 OST).mp3",
          "identifier": "JeremySouleFearNotThisNightPianoCoverInstrumentalGuildWars2OST",
          "title": "Jeremy Soule Fear Not This Night Piano Cover Instrumental ( Guild Wars 2 OST)",
          "creator": "",
          "durationSeconds": 301,
          "url": "https://archive.org/download/JeremySouleFearNotThisNightPianoCoverInstrumentalGuildWars2OST/Jeremy%20Soule%20-%20Fear%20Not%20This%20Night%20-Piano%20Cover%20Instrumental%20%28Guild%20Wars%202%20OST%29.mp3",
          "tags": "jeremy soule fear not this night piano cover instrumental ( guild wars 2 ost) ",
          "category": "ke_toan",
          "categoryScore": 5
        },
        {
          "id": "coldjorgemendezsadpianoviolininstrumental:Cold - Jorge Méndez (Sad Piano  Violin Instrumental).mp3",
          "identifier": "coldjorgemendezsadpianoviolininstrumental",
          "title": "Cold Jorge Méndez ( Sad Piano Violin Instrumental)",
          "creator": "",
          "durationSeconds": 297,
          "url": "https://archive.org/download/coldjorgemendezsadpianoviolininstrumental/Cold%20-%20Jorge%20M%C3%A9ndez%20%28Sad%20Piano%20%20Violin%20Instrumental%29.mp3",
          "tags": "cold jorge méndez ( sad piano violin instrumental) ",
          "category": "ke_toan",
          "categoryScore": 5
        },
        {
          "id": "el-me-levantara-piano-heaven-instrumental-musica-para-meditar-musica-para-orar-h-efy-9-wbj-3u-4:Él Me Levantará _ Piano _ Heaven Instrumental _ Música para Meditar _ Música Para Orar [hEFy9WBJ3u4].mp3",
          "identifier": "el-me-levantara-piano-heaven-instrumental-musica-para-meditar-musica-para-orar-h-efy-9-wbj-3u-4",
          "title": "Él Me Levantará Piano Heaven Instrumental Música Para Meditar Música Para Orar [h EFy 9 WBJ 3u 4]",
          "creator": "",
          "durationSeconds": 296,
          "url": "https://archive.org/download/el-me-levantara-piano-heaven-instrumental-musica-para-meditar-musica-para-orar-h-efy-9-wbj-3u-4/%C3%89l%20Me%20Levantar%C3%A1%20_%20Piano%20_%20Heaven%20Instrumental%20_%20M%C3%BAsica%20para%20Meditar%20_%20M%C3%BAsica%20Para%20Orar%20%5BhEFy9WBJ3u4%5D.mp3",
          "tags": "él me levantará piano heaven instrumental música para meditar música para orar [h efy 9 wbj 3u 4] ",
          "category": "ke_toan",
          "categoryScore": 5
        },
        {
          "id": "acidplanet-audio-01522231:01522231.mp3",
          "identifier": "acidplanet-audio-01522231",
          "title": "Piano Medley (Promo Instrumental)",
          "creator": "NEUROTIC.UNIQUE.",
          "durationSeconds": 288,
          "url": "https://archive.org/download/acidplanet-audio-01522231/01522231.mp3",
          "tags": "piano medley (promo instrumental) neurotic.unique.",
          "category": "ke_toan",
          "categoryScore": 5
        },
        {
          "id": "love-songs-piano-sax-instrumental-collection:TRACK016.MP3",
          "identifier": "love-songs-piano-sax-instrumental-collection",
          "title": "Love Songs Piano & Sax Instrumental Collection",
          "creator": "Alpha Music Corporation",
          "durationSeconds": 286,
          "url": "https://archive.org/download/love-songs-piano-sax-instrumental-collection/TRACK016.MP3",
          "tags": "love songs piano & sax instrumental collection alpha music corporation",
          "category": "ke_toan",
          "categoryScore": 5
        },
        {
          "id": "TitanicpianoInstrumental:Titanic (piano-instrumental).mp3",
          "identifier": "TitanicpianoInstrumental",
          "title": "Titanic (piano Instrumental)",
          "creator": "",
          "durationSeconds": 285,
          "url": "https://archive.org/download/TitanicpianoInstrumental/Titanic%20%28piano-instrumental%29.mp3",
          "tags": "titanic (piano instrumental) ",
          "category": "ke_toan",
          "categoryScore": 5
        },
        {
          "id": "KennyGInstrumentalWeddingSongsPianoFirstLove:kenny g- instrumental wedding songs - piano - first love.mp3",
          "identifier": "KennyGInstrumentalWeddingSongsPianoFirstLove",
          "title": "Kenny G Instrumental Wedding Songs Piano First Love",
          "creator": "creador del contenido",
          "durationSeconds": 284,
          "url": "https://archive.org/download/KennyGInstrumentalWeddingSongsPianoFirstLove/kenny%20g-%20instrumental%20wedding%20songs%20-%20piano%20-%20first%20love.mp3",
          "tags": "kenny g instrumental wedding songs piano first love creador del contenido",
          "category": "ke_toan",
          "categoryScore": 5
        },
        {
          "id": "HipHopInstrumentalPianoUnderground:Hip Hop Instrumental-{Piano}-{Underground}.mp3",
          "identifier": "HipHopInstrumentalPianoUnderground",
          "title": "Hip Hop Instrumental { Piano} { Underground}",
          "creator": "",
          "durationSeconds": 280,
          "url": "https://archive.org/download/HipHopInstrumentalPianoUnderground/Hip%20Hop%20Instrumental-%7BPiano%7D-%7BUnderground%7D.mp3",
          "tags": "hip hop instrumental { piano} { underground} ",
          "category": "ke_toan",
          "categoryScore": 5
        },
        {
          "id": "remix-nin-com-audio-14958:vikatine - A Warm Place - piano instrumental.mp3",
          "identifier": "remix-nin-com-audio-14958",
          "title": "A Warm Place - piano instrumental",
          "creator": "vikatine",
          "durationSeconds": 280,
          "url": "https://archive.org/download/remix-nin-com-audio-14958/vikatine%20-%20A%20Warm%20Place%20-%20piano%20instrumental.mp3",
          "tags": "a warm place - piano instrumental vikatine",
          "category": "ke_toan",
          "categoryScore": 5
        },
        {
          "id": "palu-ngataku-instrumental-piano-high-quality-audio-lagu-daerah-sulawesi-tengah:PALU NGATAKU INSTRUMENTAL (PIANO) HIGH QUALITY AUDIO - LAGU DAERAH SULAWESI TENGAH.mp3",
          "identifier": "palu-ngataku-instrumental-piano-high-quality-audio-lagu-daerah-sulawesi-tengah",
          "title": "PALU NGATAKU INSTRUMENTAL ( PIANO) HIGH QUALITY AUDIO LAGU DAERAH SULAWESI TENGAH",
          "creator": "",
          "durationSeconds": 273,
          "url": "https://archive.org/download/palu-ngataku-instrumental-piano-high-quality-audio-lagu-daerah-sulawesi-tengah/PALU%20NGATAKU%20INSTRUMENTAL%20%28PIANO%29%20HIGH%20QUALITY%20AUDIO%20-%20LAGU%20DAERAH%20SULAWESI%20TENGAH.mp3",
          "tags": "palu ngataku instrumental ( piano) high quality audio lagu daerah sulawesi tengah ",
          "category": "ke_toan",
          "categoryScore": 5
        },
        {
          "id": "WinterSonataMyMemoryPianoInstrumental128Kbps:Winter Sonata - My Memory (Piano Instrumental) (128  kbps).mp3",
          "identifier": "WinterSonataMyMemoryPianoInstrumental128Kbps",
          "title": "Winter Sonata My Memory ( Piano Instrumental) ( 128 Kbps)",
          "creator": "ntongdarullah",
          "durationSeconds": 268,
          "url": "https://archive.org/download/WinterSonataMyMemoryPianoInstrumental128Kbps/Winter%20Sonata%20-%20My%20Memory%20%28Piano%20Instrumental%29%20%28128%20%20kbps%29.mp3",
          "tags": "winter sonata my memory ( piano instrumental) ( 128 kbps) ntongdarullah",
          "category": "ke_toan",
          "categoryScore": 5
        },
        {
          "id": "remix-nin-com-audio-12515:Notion_Undertone - Hurt (Piano & Strings Instrumental).mp3",
          "identifier": "remix-nin-com-audio-12515",
          "title": "Hurt (Piano & Strings Instrumental)",
          "creator": "Notion_Undertone",
          "durationSeconds": 252,
          "url": "https://archive.org/download/remix-nin-com-audio-12515/Notion_Undertone%20-%20Hurt%20%28Piano%20%26%20Strings%20Instrumental%29.mp3",
          "tags": "hurt (piano & strings instrumental) notion_undertone",
          "category": "ke_toan",
          "categoryScore": 5
        },
        {
          "id": "MECD-2K-99036_202602:TRACK013.MP3",
          "identifier": "MECD-2K-99036_202602",
          "title": "MECD-2K-99036 \"An Instrumental Journey : It Might Be You (Piano Collection)  | The Lighthouse Piano & Orchestra\" (Audio CD ripped)",
          "creator": "Alpha Music Corporation",
          "durationSeconds": 251,
          "url": "https://archive.org/download/MECD-2K-99036_202602/TRACK013.MP3",
          "tags": "mecd-2k-99036 \"an instrumental journey : it might be you (piano collection)  | the lighthouse piano & orchestra\" (audio cd ripped) alpha music corporation",
          "category": "ke_toan",
          "categoryScore": 5
        },
        {
          "id": "DontYouWorryChildInstrumentalThePianoGuys:Don't You Worry Child (Instrumental) - The Piano Guys.mp3",
          "identifier": "DontYouWorryChildInstrumentalThePianoGuys",
          "title": "Don't You Worry Child ( Instrumental) The Piano Guys",
          "creator": "",
          "durationSeconds": 243,
          "url": "https://archive.org/download/DontYouWorryChildInstrumentalThePianoGuys/Don%27t%20You%20Worry%20Child%20%28Instrumental%29%20-%20The%20Piano%20Guys.mp3",
          "tags": "don't you worry child ( instrumental) the piano guys ",
          "category": "ke_toan",
          "categoryScore": 5
        },
        {
          "id": "modern-talking-world-youre-my-heart-relaxing-version-instrumental:𝓜𝓸𝓭𝓮𝓻𝓷 𝓣𝓪𝓵𝓴𝓲𝓷𝓰 𝓦𝓸𝓻𝓵𝓭 —Youre my Heart  (Relaxing version Instrumental).mp3",
          "identifier": "modern-talking-world-youre-my-heart-relaxing-version-instrumental",
          "title": "𝓜𝓸𝓭𝓮𝓻𝓷 𝓣𝓪𝓵𝓴𝓲𝓷𝓰 𝓦𝓸𝓻𝓵𝓭 — Youre My Heart ( Relaxing Version Instrumental)",
          "creator": "",
          "durationSeconds": 242,
          "url": "https://archive.org/download/modern-talking-world-youre-my-heart-relaxing-version-instrumental/%F0%9D%93%9C%F0%9D%93%B8%F0%9D%93%AD%F0%9D%93%AE%F0%9D%93%BB%F0%9D%93%B7%20%F0%9D%93%A3%F0%9D%93%AA%F0%9D%93%B5%F0%9D%93%B4%F0%9D%93%B2%F0%9D%93%B7%F0%9D%93%B0%20%F0%9D%93%A6%F0%9D%93%B8%F0%9D%93%BB%F0%9D%93%B5%F0%9D%93%AD%20%E2%80%94Youre%20my%20Heart%20%20%28Relaxing%20version%20Instrumental%29.mp3",
          "tags": "𝓜𝓸𝓭𝓮𝓻𝓷 𝓣𝓪𝓵𝓴𝓲𝓷𝓰 𝓦𝓸𝓻𝓵𝓭 — youre my heart ( relaxing version instrumental) ",
          "category": "ke_toan",
          "categoryScore": 5
        },
        {
          "id": "UAndITheWeddingSongPianoInstrumental:Amazed (Lonestar) Wedding music Piano (1).mp3",
          "identifier": "UAndITheWeddingSongPianoInstrumental",
          "title": "U And I The Wedding Song( Piano Instrumental)",
          "creator": "",
          "durationSeconds": 242,
          "url": "https://archive.org/download/UAndITheWeddingSongPianoInstrumental/Amazed%20%28Lonestar%29%20Wedding%20music%20Piano%20%281%29.mp3",
          "tags": "u and i the wedding song( piano instrumental) ",
          "category": "ke_toan",
          "categoryScore": 5
        },
        {
          "id": "jamendo-167466:03-1438452-DANYRITHMMAN-SOLO POR TI 2016.mp3",
          "identifier": "jamendo-167466",
          "title": "DANYRITHMMAN - BLUE MARIA INSTRUMENTAL PIANO",
          "creator": "DANYRITHMMAN",
          "durationSeconds": 230,
          "url": "https://archive.org/download/jamendo-167466/03-1438452-DANYRITHMMAN-SOLO%20POR%20TI%202016.mp3",
          "tags": "danyrithmman - blue maria instrumental piano danyrithmman",
          "category": "ke_toan",
          "categoryScore": 5
        },
        {
          "id": "y-2meta.app-hallelujah-instrumental-cover-piano-violin-cello-320-kbps-mp-3cut.net:Y2meta.app - Hallelujah - Instrumental (Cover) _ Piano Violin Cello (320 kbps) (mp3cut.net).mp3",
          "identifier": "y-2meta.app-hallelujah-instrumental-cover-piano-violin-cello-320-kbps-mp-3cut.net",
          "title": "Y 2meta.app Hallelujah Instrumental ( Cover) Piano Violin Cello ( 320 Kbps) (mp 3cut.net)",
          "creator": "",
          "durationSeconds": 229,
          "url": "https://archive.org/download/y-2meta.app-hallelujah-instrumental-cover-piano-violin-cello-320-kbps-mp-3cut.net/Y2meta.app%20-%20Hallelujah%20-%20Instrumental%20%28Cover%29%20_%20Piano%20Violin%20Cello%20%28320%20kbps%29%20%28mp3cut.net%29.mp3",
          "tags": "y 2meta.app hallelujah instrumental ( cover) piano violin cello ( 320 kbps) (mp 3cut.net) ",
          "category": "ke_toan",
          "categoryScore": 5
        },
        {
          "id": "caribbean-blue-enya.-piano-version.-versao-piano.-instrumental.-the-celts-in-description.-seladon:Caribbean blue-Enya. Piano version. Versăo piano. Instrumental. The celts in description. - Séladon.mp3",
          "identifier": "caribbean-blue-enya.-piano-version.-versao-piano.-instrumental.-the-celts-in-description.-seladon",
          "title": "Caribbean Blue Enya. Piano Version. Versăo Piano. Instrumental. The Celts In Description. Séladon",
          "creator": "",
          "durationSeconds": 225,
          "url": "https://archive.org/download/caribbean-blue-enya.-piano-version.-versao-piano.-instrumental.-the-celts-in-description.-seladon/Caribbean%20blue-Enya.%20Piano%20version.%20Vers%C4%83o%20piano.%20Instrumental.%20The%20celts%20in%20description.%20-%20S%C3%A9ladon.mp3",
          "tags": "caribbean blue enya. piano version. versăo piano. instrumental. the celts in description. séladon ",
          "category": "ke_toan",
          "categoryScore": 5
        },
        {
          "id": "ThisWhatYouCameForPianoInstrumental:Piano This What You Came For.mp3",
          "identifier": "ThisWhatYouCameForPianoInstrumental",
          "title": "This What You Came For (Piano Instrumental)",
          "creator": "Jonces Rios",
          "durationSeconds": 221,
          "url": "https://archive.org/download/ThisWhatYouCameForPianoInstrumental/Piano%20This%20What%20You%20Came%20For.mp3",
          "tags": "this what you came for (piano instrumental) jonces rios",
          "category": "ke_toan",
          "categoryScore": 5
        },
        {
          "id": "instrumental-piano-para-componer-letra-cancio-n-uso-libre-gratis-instrumentales-leo.:INSTRUMENTAL PIANO PARA COMPONER LETRA CANCIÓN _ USO LIBRE GRATIS - Instrumentales Leo..mp3",
          "identifier": "instrumental-piano-para-componer-letra-cancio-n-uso-libre-gratis-instrumentales-leo.",
          "title": "INSTRUMENTAL PIANO PARA COMPONER LETRA CANCIÓ N USO LIBRE GRATIS Instrumentales Leo.",
          "creator": "Intrumentales Leo",
          "durationSeconds": 215,
          "url": "https://archive.org/download/instrumental-piano-para-componer-letra-cancio-n-uso-libre-gratis-instrumentales-leo./INSTRUMENTAL%20PIANO%20PARA%20COMPONER%20LETRA%20CANCI%C3%93N%20_%20USO%20LIBRE%20GRATIS%20-%20Instrumentales%20Leo..mp3",
          "tags": "instrumental piano para componer letra canció n uso libre gratis instrumentales leo. intrumentales leo",
          "category": "ke_toan",
          "categoryScore": 5
        },
        {
          "id": "pelos-prados-e-campinas-salmo-22-piano-instrumental:Pelos_Prados_e_Campinas_-_Salmo_22_-_Piano_Instrumental.mp3",
          "identifier": "pelos-prados-e-campinas-salmo-22-piano-instrumental",
          "title": "Pelos Prados E Campinas Salmo 22 Piano Instrumental",
          "creator": "",
          "durationSeconds": 207,
          "url": "https://archive.org/download/pelos-prados-e-campinas-salmo-22-piano-instrumental/Pelos_Prados_e_Campinas_-_Salmo_22_-_Piano_Instrumental.mp3",
          "tags": "pelos prados e campinas salmo 22 piano instrumental ",
          "category": "ke_toan",
          "categoryScore": 5
        },
        {
          "id": "o-holy-night-piano-and-violins-instrumental-o-free-christmas-music_202412:O Holy Night - Piano and Violins Instrumental • Free Christmas Music.mp3",
          "identifier": "o-holy-night-piano-and-violins-instrumental-o-free-christmas-music_202412",
          "title": "O Holy Night Piano And Violins Instrumental • Free Christmas Music",
          "creator": "",
          "durationSeconds": 199,
          "url": "https://archive.org/download/o-holy-night-piano-and-violins-instrumental-o-free-christmas-music_202412/O%20Holy%20Night%20-%20Piano%20and%20Violins%20Instrumental%20%E2%80%A2%20Free%20Christmas%20Music.mp3",
          "tags": "o holy night piano and violins instrumental • free christmas music ",
          "category": "ke_toan",
          "categoryScore": 5
        },
        {
          "id": "o-holy-night-piano-and-violins-instrumental-o-free-christmas-music:O Holy Night - Piano and Violins Instrumental • Free Christmas Music.mp3",
          "identifier": "o-holy-night-piano-and-violins-instrumental-o-free-christmas-music",
          "title": "O Holy Night Piano And Violins Instrumental • Free Christmas Music",
          "creator": "",
          "durationSeconds": 199,
          "url": "https://archive.org/download/o-holy-night-piano-and-violins-instrumental-o-free-christmas-music/O%20Holy%20Night%20-%20Piano%20and%20Violins%20Instrumental%20%E2%80%A2%20Free%20Christmas%20Music.mp3",
          "tags": "o holy night piano and violins instrumental • free christmas music ",
          "category": "ke_toan",
          "categoryScore": 5
        },
        {
          "id": "jamendo-223191:01-1585888-Macroform-Cheerful Piano Rock Instrumental.mp3",
          "identifier": "jamendo-223191",
          "title": "Macroform - Cheerful Piano Rock Instrumental",
          "creator": "Macroform",
          "durationSeconds": 192,
          "url": "https://archive.org/download/jamendo-223191/01-1585888-Macroform-Cheerful%20Piano%20Rock%20Instrumental.mp3",
          "tags": "macroform - cheerful piano rock instrumental macroform",
          "category": "ke_toan",
          "categoryScore": 5
        },
        {
          "id": "remix-nin-com-audio-21015:echoesofsilence - Hidden In Sight [Piano Instrumental].mp3",
          "identifier": "remix-nin-com-audio-21015",
          "title": "Hidden In Sight [Piano Instrumental]",
          "creator": "echoesofsilence",
          "durationSeconds": 191,
          "url": "https://archive.org/download/remix-nin-com-audio-21015/echoesofsilence%20-%20Hidden%20In%20Sight%20%5BPiano%20Instrumental%5D.mp3",
          "tags": "hidden in sight [piano instrumental] echoesofsilence",
          "category": "ke_toan",
          "categoryScore": 5
        },
        {
          "id": "away-in-a-manger-instrumental-christmas-music-piano-violin-orchestra:Away in a Manger - Instrumental Christmas Music Piano, Violin & Orchestra.mp3",
          "identifier": "away-in-a-manger-instrumental-christmas-music-piano-violin-orchestra",
          "title": "Away In A Manger Instrumental Christmas Music Piano, Violin & Orchestra",
          "creator": "Rev Austin Fleming",
          "durationSeconds": 183,
          "url": "https://archive.org/download/away-in-a-manger-instrumental-christmas-music-piano-violin-orchestra/Away%20in%20a%20Manger%20-%20Instrumental%20Christmas%20Music%20Piano%2C%20Violin%20%26%20Orchestra.mp3",
          "tags": "away in a manger instrumental christmas music piano, violin & orchestra rev austin fleming",
          "category": "ke_toan",
          "categoryScore": 5
        },
        {
          "id": "AFRICUSSIONMUSICTLM-ICACAprayerpointsmusic51InstrumentalHymnsPiano:ICACAprayerpointsmusic - 51 Instrumental Hymns Piano.mp3",
          "identifier": "AFRICUSSIONMUSICTLM-ICACAprayerpointsmusic51InstrumentalHymnsPiano",
          "title": "AFRICUSSION MUSIC TLM-ICACAprayerpointsmusic 51 Instrumental Hymns Piano",
          "creator": "",
          "durationSeconds": 3676,
          "url": "https://archive.org/download/AFRICUSSIONMUSICTLM-ICACAprayerpointsmusic51InstrumentalHymnsPiano/ICACAprayerpointsmusic%20-%2051%20Instrumental%20Hymns%20Piano.mp3",
          "tags": "africussion music tlm-icacaprayerpointsmusic 51 instrumental hymns piano ",
          "category": "ke_toan",
          "categoryScore": 4
        },
        {
          "id": "ICACAprayerpointsmusic51InstrumentalHymnsPiano:ICACAprayerpointsmusic - 51 Instrumental Hymns Piano.mp3",
          "identifier": "ICACAprayerpointsmusic51InstrumentalHymnsPiano",
          "title": "ICACAprayerpointsmusic 51 Instrumental Hymns Piano",
          "creator": "",
          "durationSeconds": 3676,
          "url": "https://archive.org/download/ICACAprayerpointsmusic51InstrumentalHymnsPiano/ICACAprayerpointsmusic%20-%2051%20Instrumental%20Hymns%20Piano.mp3",
          "tags": "icacaprayerpointsmusic 51 instrumental hymns piano ",
          "category": "ke_toan",
          "categoryScore": 4
        },
        {
          "id": "instrumental-piano-musica-cristiana:INSTRUMENTAL PIANO    MUSICA CRISTIANA.mp3",
          "identifier": "instrumental-piano-musica-cristiana",
          "title": "INSTRUMENTAL PIANO MUSICA CRISTIANA",
          "creator": "chili willy",
          "durationSeconds": 3605,
          "url": "https://archive.org/download/instrumental-piano-musica-cristiana/INSTRUMENTAL%20PIANO%20%20%20%20MUSICA%20CRISTIANA.mp3",
          "tags": "instrumental piano musica cristiana chili willy",
          "category": "ke_toan",
          "categoryScore": 4
        },
        {
          "id": "top-30-piano-covers-of-popular-songs-2019-best-instrumental-piano-covers-all-time-wm-fz-6-cd-mte:TOP 10 Alan Walker PIANO COVERS on YOUTUBE 🎹_Nzd_TNxurIg.mp3",
          "identifier": "top-30-piano-covers-of-popular-songs-2019-best-instrumental-piano-covers-all-time-wm-fz-6-cd-mte",
          "title": "Top 30 Piano Covers Of Popular Songs 2019 Best Instrumental Piano Covers All Time Wm Fz 6 CD MTE",
          "creator": "",
          "durationSeconds": 3333,
          "url": "https://archive.org/download/top-30-piano-covers-of-popular-songs-2019-best-instrumental-piano-covers-all-time-wm-fz-6-cd-mte/TOP%2010%20Alan%20Walker%20PIANO%20COVERS%20on%20YOUTUBE%20%F0%9F%8E%B9_Nzd_TNxurIg.mp3",
          "tags": "top 30 piano covers of popular songs 2019 best instrumental piano covers all time wm fz 6 cd mte ",
          "category": "ke_toan",
          "categoryScore": 4
        },
        {
          "id": "musica-gospel-piano-instrumental-para-orar-falar-com-deus:Musica Gospel Piano Instrumental para Orar _ Falar com Deus.mp3",
          "identifier": "musica-gospel-piano-instrumental-para-orar-falar-com-deus",
          "title": "Musica Gospel Piano Instrumental Para Orar Falar Com Deus",
          "creator": "",
          "durationSeconds": 2743,
          "url": "https://archive.org/download/musica-gospel-piano-instrumental-para-orar-falar-com-deus/Musica%20Gospel%20Piano%20Instrumental%20para%20Orar%20_%20Falar%20com%20Deus.mp3",
          "tags": "musica gospel piano instrumental para orar falar com deus ",
          "category": "ke_toan",
          "categoryScore": 4
        },
        {
          "id": "musica-gospel-piano-instrumental-para-orar-falar-com-deus_202404:Musica Gospel Piano Instrumental para Orar _ Falar com Deus.mp3",
          "identifier": "musica-gospel-piano-instrumental-para-orar-falar-com-deus_202404",
          "title": "Musica Gospel Piano Instrumental Para Orar Falar Com Deus",
          "creator": "",
          "durationSeconds": 2743,
          "url": "https://archive.org/download/musica-gospel-piano-instrumental-para-orar-falar-com-deus_202404/Musica%20Gospel%20Piano%20Instrumental%20para%20Orar%20_%20Falar%20com%20Deus.mp3",
          "tags": "musica gospel piano instrumental para orar falar com deus ",
          "category": "ke_toan",
          "categoryScore": 4
        },
        {
          "id": "piano-on-the-beach-meditation-2:Piano on the beach meditation (2).mp3",
          "identifier": "piano-on-the-beach-meditation-2",
          "title": "Piano On The Beach Meditation ( 2)",
          "creator": "",
          "durationSeconds": 3709,
          "url": "https://archive.org/download/piano-on-the-beach-meditation-2/Piano%20on%20the%20beach%20meditation%20%282%29.mp3",
          "tags": "piano on the beach meditation ( 2) ",
          "category": "ke_toan",
          "categoryScore": 3
        },
        {
          "id": "gentle-piano-meditation-2:Gentle piano meditation (2).mp3",
          "identifier": "gentle-piano-meditation-2",
          "title": "Gentle Piano Meditation ( 2)",
          "creator": "",
          "durationSeconds": 3633,
          "url": "https://archive.org/download/gentle-piano-meditation-2/Gentle%20piano%20meditation%20%282%29.mp3",
          "tags": "gentle piano meditation ( 2) ",
          "category": "ke_toan",
          "categoryScore": 3
        },
        {
          "id": "1-hour-of-relaxing-music-chinese-bamboo-flute-meditation-sleep:صوت البحر - صوت الامواج - صوت البحر مع موسيقى - اصوات الطبيعة - ساعة كاملة Seaside with music.mp3",
          "identifier": "1-hour-of-relaxing-music-chinese-bamboo-flute-meditation-sleep",
          "title": "1 HOUR Of Relaxing Music Chinese Bamboo Flute Meditation Sleep من اروع الموسيقى الصينية مع ناي",
          "creator": "",
          "durationSeconds": 3612,
          "url": "https://archive.org/download/1-hour-of-relaxing-music-chinese-bamboo-flute-meditation-sleep/%D8%B5%D9%88%D8%AA%20%D8%A7%D9%84%D8%A8%D8%AD%D8%B1%20-%20%D8%B5%D9%88%D8%AA%20%D8%A7%D9%84%D8%A7%D9%85%D9%88%D8%A7%D8%AC%20-%20%D8%B5%D9%88%D8%AA%20%D8%A7%D9%84%D8%A8%D8%AD%D8%B1%20%D9%85%D8%B9%20%D9%85%D9%88%D8%B3%D9%8A%D9%82%D9%89%20-%20%D8%A7%D8%B5%D9%88%D8%A7%D8%AA%20%D8%A7%D9%84%D8%B7%D8%A8%D9%8A%D8%B9%D8%A9%20-%20%D8%B3%D8%A7%D8%B9%D8%A9%20%D9%83%D8%A7%D9%85%D9%84%D8%A9%20Seaside%20with%20music.mp3",
          "tags": "1 hour of relaxing music chinese bamboo flute meditation sleep من اروع الموسيقى الصينية مع ناي ",
          "category": "ke_toan",
          "categoryScore": 3
        },
        {
          "id": "1-hour-of-best-relaxing-music-bamboo-flute-sleep-music-meditation-music-peaceful-sleep-music:1 HOUR of Best Relaxing Music _ Bamboo Flute _ Sleep Music _ Meditation Music _ Peaceful Sleep Music.m4a",
          "identifier": "1-hour-of-best-relaxing-music-bamboo-flute-sleep-music-meditation-music-peaceful-sleep-music",
          "title": "1 HOUR Of Best Relaxing Music Bamboo Flute Sleep Music Meditation Music Peaceful Sleep Music",
          "creator": "TANSEL MARTİN",
          "durationSeconds": 3406,
          "url": "https://archive.org/download/1-hour-of-best-relaxing-music-bamboo-flute-sleep-music-meditation-music-peaceful-sleep-music/1%20HOUR%20of%20Best%20Relaxing%20Music%20_%20Bamboo%20Flute%20_%20Sleep%20Music%20_%20Meditation%20Music%20_%20Peaceful%20Sleep%20Music.m4a",
          "tags": "1 hour of best relaxing music bamboo flute sleep music meditation music peaceful sleep music tansel marti̇n",
          "category": "ke_toan",
          "categoryScore": 3
        }
      ]
    },
    "phap_che": {
      "label": "Phap che - Tinh va ro",
      "description": "Khong gian nhac nghiem, giu dau oc ro rang khi doc dieu khoan",
      "tracks": [
        {
          "id": "ambient-piano-meditation-2:Ambient piano meditation (2).mp3",
          "identifier": "ambient-piano-meditation-2",
          "title": "Ambient Piano Meditation ( 2)",
          "creator": "",
          "durationSeconds": 3928,
          "url": "https://archive.org/download/ambient-piano-meditation-2/Ambient%20piano%20meditation%20%282%29.mp3",
          "tags": "ambient piano meditation ( 2) ",
          "category": "phap_che",
          "categoryScore": 5
        },
        {
          "id": "blue-skies_202510: blue skies .m4a",
          "identifier": "blue-skies_202510",
          "title": "Ambient Solo Piano",
          "creator": "",
          "durationSeconds": 389,
          "url": "https://archive.org/download/blue-skies_202510/%20blue%20skies%20.m4a",
          "tags": "ambient solo piano ",
          "category": "phap_che",
          "categoryScore": 5
        }
      ]
    },
    "kinh_doanh": {
      "label": "Kinh doanh - Tich cuc va ben bi",
      "description": "Nang luong vua du, khong gay xao nhang",
      "tracks": []
    },
    "sang_tao": {
      "label": "Sang tao - Mo rong y tuong",
      "description": "Ambient/nhac cu nhe giup vao trang thai flow",
      "tracks": [
        {
          "id": "cior-20-agitation-phi-studies-on-ambient-bass-guitar:02 - Cairo 1904 (for electric bass and time woven filter matrix).mp3",
          "identifier": "cior-20-agitation-phi-studies-on-ambient-bass-guitar",
          "title": "Agitation Phi - Studies On Ambient Bass Guitar (2017) (CIOR-20)",
          "creator": "Agitation Phi",
          "durationSeconds": 2369,
          "url": "https://archive.org/download/cior-20-agitation-phi-studies-on-ambient-bass-guitar/02%20-%20Cairo%201904%20%28for%20electric%20bass%20and%20time%20woven%20filter%20matrix%29.mp3",
          "tags": "agitation phi - studies on ambient bass guitar (2017) (cior-20) agitation phi",
          "category": "sang_tao",
          "categoryScore": 6
        },
        {
          "id": "ambient-guitar-eq:Ambient Guitar EQ.mp3",
          "identifier": "ambient-guitar-eq",
          "title": "Ambient Guitar",
          "creator": "GARY HAYDEN",
          "durationSeconds": 1710,
          "url": "https://archive.org/download/ambient-guitar-eq/Ambient%20Guitar%20EQ.mp3",
          "tags": "ambient guitar gary hayden",
          "category": "sang_tao",
          "categoryScore": 6
        },
        {
          "id": "AmbientGuitarImprovisationsVol.1:01TheGuiltOfExistence.mp3",
          "identifier": "AmbientGuitarImprovisationsVol.1",
          "title": "Ambient Guitar Improvisations Vol.1",
          "creator": "Royce Icon",
          "durationSeconds": 712,
          "url": "https://archive.org/download/AmbientGuitarImprovisationsVol.1/01TheGuiltOfExistence.mp3",
          "tags": "ambient guitar improvisations vol.1 royce icon",
          "category": "sang_tao",
          "categoryScore": 6
        },
        {
          "id": "jamendo-157938:01-1336438-Ambient Samurai - Ichiro NAKAGAWA-Ambient Guitar For __ ___ _____.mp3",
          "identifier": "jamendo-157938",
          "title": "Ambient Samurai - Ichiro NAKAGAWA - Ambient Guitar For Hi To No Ka Na Shi Mi 　2016-4-2",
          "creator": "Ambient Samurai - Ichiro NAKAGAWA",
          "durationSeconds": 621,
          "url": "https://archive.org/download/jamendo-157938/01-1336438-Ambient%20Samurai%20-%20Ichiro%20NAKAGAWA-Ambient%20Guitar%20For%20__%20___%20_____.mp3",
          "tags": "ambient samurai - ichiro nakagawa - ambient guitar for hi to no ka na shi mi 　2016-4-2 ambient samurai - ichiro nakagawa",
          "category": "sang_tao",
          "categoryScore": 6
        },
        {
          "id": "1-hour-of-the-best-relaxing-music-bamboo-flute-meditation-music-healing-sleep-zen-peace_202007:1 HOUR of The Best Relaxing Music  Bamboo Flute  Meditation Music - Healing - Sleep - Zen - Peace.mp3",
          "identifier": "1-hour-of-the-best-relaxing-music-bamboo-flute-meditation-music-healing-sleep-zen-peace_202007",
          "title": "1 HOUR Of The Best Relaxing Music Bamboo Flute Meditation Music Healing Sleep Zen Peace",
          "creator": "",
          "durationSeconds": 3405,
          "url": "https://archive.org/download/1-hour-of-the-best-relaxing-music-bamboo-flute-meditation-music-healing-sleep-zen-peace_202007/1%20HOUR%20of%20The%20Best%20Relaxing%20Music%20%20Bamboo%20Flute%20%20Meditation%20Music%20-%20Healing%20-%20Sleep%20-%20Zen%20-%20Peace.mp3",
          "tags": "1 hour of the best relaxing music bamboo flute meditation music healing sleep zen peace ",
          "category": "sang_tao",
          "categoryScore": 5
        },
        {
          "id": "1-hour-of-the-best-relaxing-music-bamboo-flute-meditation-music-healing-sleep-zen-peace:1 HOUR of The Best Relaxing Music  Bamboo Flute  Meditation Music - Healing - Sleep - Zen - Peace.mp3",
          "identifier": "1-hour-of-the-best-relaxing-music-bamboo-flute-meditation-music-healing-sleep-zen-peace",
          "title": "1 HOUR Of The Best Relaxing Music Bamboo Flute Meditation Music Healing Sleep Zen Peace",
          "creator": "",
          "durationSeconds": 3405,
          "url": "https://archive.org/download/1-hour-of-the-best-relaxing-music-bamboo-flute-meditation-music-healing-sleep-zen-peace/1%20HOUR%20of%20The%20Best%20Relaxing%20Music%20%20Bamboo%20Flute%20%20Meditation%20Music%20-%20Healing%20-%20Sleep%20-%20Zen%20-%20Peace.mp3",
          "tags": "1 hour of the best relaxing music bamboo flute meditation music healing sleep zen peace ",
          "category": "sang_tao",
          "categoryScore": 5
        },
        {
          "id": "1HOUROfTheBestRelaxingMusicBambooFluteMeditationHealingSleepZenPeace:1 HOUR of The Best Relaxing Music  Bamboo Flute  - Meditation - Healing - Sleep - Zen - Peace.mp3",
          "identifier": "1HOUROfTheBestRelaxingMusicBambooFluteMeditationHealingSleepZenPeace",
          "title": "1 HOUR Of The Best Relaxing Music Bamboo Flute Meditation Healing Sleep Zen Peace",
          "creator": "",
          "durationSeconds": 3397,
          "url": "https://archive.org/download/1HOUROfTheBestRelaxingMusicBambooFluteMeditationHealingSleepZenPeace/1%20HOUR%20of%20The%20Best%20Relaxing%20Music%20%20Bamboo%20Flute%20%20-%20Meditation%20-%20Healing%20-%20Sleep%20-%20Zen%20-%20Peace.mp3",
          "tags": "1 hour of the best relaxing music bamboo flute meditation healing sleep zen peace ",
          "category": "sang_tao",
          "categoryScore": 5
        },
        {
          "id": "y-2mate.com-namaste-music-flute-meditation-9-bd-1y-0-tok-3o:y2mate.com - Namaste Music_ Flute Meditation_9BD1y0TOk3o.mp3",
          "identifier": "y-2mate.com-namaste-music-flute-meditation-9-bd-1y-0-tok-3o",
          "title": "Y 2mate.com Namaste Music Flute Meditation 9 BD 1y 0 TOk 3o",
          "creator": "",
          "durationSeconds": 1200,
          "url": "https://archive.org/download/y-2mate.com-namaste-music-flute-meditation-9-bd-1y-0-tok-3o/y2mate.com%20-%20Namaste%20Music_%20Flute%20Meditation_9BD1y0TOk3o.mp3",
          "tags": "y 2mate.com namaste music flute meditation 9 bd 1y 0 tok 3o ",
          "category": "sang_tao",
          "categoryScore": 5
        },
        {
          "id": "GuitarMeditation:GuitarMeditation_64kb_mp3.zip",
          "identifier": "GuitarMeditation",
          "title": "Guitar Meditation",
          "creator": "Derek Tollefson",
          "durationSeconds": 1002,
          "url": "https://archive.org/download/GuitarMeditation/GuitarMeditation_64kb_mp3.zip",
          "tags": "guitar meditation derek tollefson",
          "category": "sang_tao",
          "categoryScore": 5
        },
        {
          "id": "jamendo-176493:02-1542688-Solxis-Granular Skies.mp3",
          "identifier": "jamendo-176493",
          "title": "Solxis - Ambient Guitar",
          "creator": "Solxis",
          "durationSeconds": 270,
          "url": "https://archive.org/download/jamendo-176493/02-1542688-Solxis-Granular%20Skies.mp3",
          "tags": "solxis - ambient guitar solxis",
          "category": "sang_tao",
          "categoryScore": 5
        },
        {
          "id": "ambient-japanese-flute-music:Ambient Japanese Flute Music.mp3",
          "identifier": "ambient-japanese-flute-music",
          "title": "Ambient Japanese Flute Music",
          "creator": "",
          "durationSeconds": 4031,
          "url": "https://archive.org/download/ambient-japanese-flute-music/Ambient%20Japanese%20Flute%20Music.mp3",
          "tags": "ambient japanese flute music ",
          "category": "sang_tao",
          "categoryScore": 4
        },
        {
          "id": "flute-meditation:Flute_Meditation.mp3",
          "identifier": "flute-meditation",
          "title": "Flute Meditation",
          "creator": "",
          "durationSeconds": 570,
          "url": "https://archive.org/download/flute-meditation/Flute_Meditation.mp3",
          "tags": "flute meditation ",
          "category": "sang_tao",
          "categoryScore": 4
        },
        {
          "id": "BapuFluteMeditationWithBansuri:BapuFlute-Meditate2.ogg",
          "identifier": "BapuFluteMeditationWithBansuri",
          "title": "Bapu Flute Meditation With Bansuri ",
          "creator": "Bapu Padmanabha",
          "durationSeconds": 297,
          "url": "https://archive.org/download/BapuFluteMeditationWithBansuri/BapuFlute-Meditate2.ogg",
          "tags": "bapu flute meditation with bansuri  bapu padmanabha",
          "category": "sang_tao",
          "categoryScore": 4
        },
        {
          "id": "BapuFluteMeditationWithBambooFlute:BapuFlute-Meditate1.ogg",
          "identifier": "BapuFluteMeditationWithBambooFlute",
          "title": "Bapu Flute Meditation with Bamboo Flute",
          "creator": "Bapu Padmanabha",
          "durationSeconds": 257,
          "url": "https://archive.org/download/BapuFluteMeditationWithBambooFlute/BapuFlute-Meditate1.ogg",
          "tags": "bapu flute meditation with bamboo flute bapu padmanabha",
          "category": "sang_tao",
          "categoryScore": 4
        },
        {
          "id": "sun-and-moon-meditation-1-hour-handpan-guitar-music-malte-marten-luna-mando:Sun and Moon Meditation  1 hour handpan & guitar music  Malte Marten & Luna Mando.mp3",
          "identifier": "sun-and-moon-meditation-1-hour-handpan-guitar-music-malte-marten-luna-mando",
          "title": "Sun And Moon Meditation 1 Hour Handpan & Guitar Music Malte Marten & Luna Mando",
          "creator": "",
          "durationSeconds": 3993,
          "url": "https://archive.org/download/sun-and-moon-meditation-1-hour-handpan-guitar-music-malte-marten-luna-mando/Sun%20and%20Moon%20Meditation%20%201%20hour%20handpan%20%26%20guitar%20music%20%20Malte%20Marten%20%26%20Luna%20Mando.mp3",
          "tags": "sun and moon meditation 1 hour handpan & guitar music malte marten & luna mando ",
          "category": "sang_tao",
          "categoryScore": 3
        }
      ]
    }
  }
}